Workbook

Sheet Người 1
A1: Nhóm | B1: title | C1: reviewsCount (max 1035) | D1: totalScore | E1: street | F1: state | G1: searchString | H1: url | I1: reviewsCount gốc
A2: Nhóm 1 | B2: Pizza 4P's Hoang Van Thu | C2: 1035 | D2: 4.8 | E2: quan, 8 Hoàng Văn Thụ | F2: Hai Chau, Da Nang | G2: Quán pizza | H2: https://www.google.com/maps/search/?api=1&query=Pizza%204P's%20Hoang%20Van%20Thu&query_place_id=ChIJqUAP38wZQjERRq1t5kQSTdI | I2: 17061
A3: Nhóm 1 | B3: Nhà hàng Madame Lân | C3: 1035 | D3: 4.3 | E3: 04 Bạch Đằng | F3: Hải Châu, Đà Nẵng | G3: Nhà hàng | H3: https://www.google.com/maps/search/?api=1&query=Nh%C3%A0%20h%C3%A0ng%20Madame%20L%C3%A2n&query_place_id=ChIJe0VNzjEYQjERImNbpnRF9cI | I3: 14304
A4: Nhóm 1 | B4: Pizza 4P's indochina Đà Nẵng | C4: 1035 | D4: 4.9 | E4: 74 Bạch Đằng | F4: Hải Châu, Đà Nẵng | G4: Quán ăn tối | H4: https://www.google.com/maps/search/?api=1&query=Pizza%204P's%20indochina%20%C4%90%C3%A0%20N%E1%BA%B5ng&query_place_id=ChIJCe8L9TwZQjERLsIy5OgdG28 | I4: 13724
A5: Nhóm 1 | B5: Bánh Xèo Bà Dưỡng | C5: 1035 | D5: 4.3 | E5: 280/23 Hoàng Diệu | F5: Hải Châu, Đà Nẵng | G5: restaurant | H5: https://www.google.com/maps/search/?api=1&query=B%C3%A1nh%20X%C3%A8o%20B%C3%A0%20D%C6%B0%E1%BB%A1ng&query_place_id=ChIJrSiIJ8oZQjERn2-PvhzOCuU | I5: 10812
A6: Nhóm 1 | B6: XÓM MỚI GARDEN | C6: 1035 | D6: 4.9 | E6: 222 Trần Phú | F6: Hải Châu, Đà Nẵng | G6: Nhà hàng Hàn Quốc | H6: https://www.google.com/maps/search/?api=1&query=X%C3%93M%20M%E1%BB%9AI%20GARDEN&query_place_id=ChIJjaiK7LgZQjERSQvPDP9gnVQ | I6: 10255
A7: Nhóm 1 | B7: Cộng Cà Phê | C7: 1035 | D7: 4.1 | E7: 98-96 Bạch Đằng | F7: Hai Chau, Da Nang | G7: Quán cà phê | H7: https://www.google.com/maps/search/?api=1&query=C%E1%BB%99ng%20C%C3%A0%20Ph%C3%AA&query_place_id=ChIJi0bpGjIYQjERRodYRF89PH8 | I7: 10196
A8: Nhóm 1 | B8: Ăn Thôi | C8: 1035 | D8: 4.8 | E8: 114 Bạch Đằng | F8: Hải Châu, Đà Nẵng | G8: Nhà hàng Việt Nam | H8: https://www.google.com/maps/search/?api=1&query=%C4%82n%20Th%C3%B4i&query_place_id=ChIJYVPRIUkZQjERH-v3yrc3lt0 | I8: 8195
A9: Nhóm 1 | B9: Bún thịt nướng Bà Trai | C9: 744 | D9: 4.2 | E9: 194 Đống Đa | F9: Hải Châu, Đà Nẵng | G9: Quán bún | H9: https://www.google.com/maps/search/?api=1&query=B%C3%BAn%20th%E1%BB%8Bt%20n%C6%B0%E1%BB%9Bng%20B%C3%A0%20Trai&query_place_id=ChIJ1a0JATkYQjERRlklbLmP9rg | I9: 744
A10: Nhóm 1 | B10: Bánh Mì Quốc Doanh Bà Đức | C10: 11 | D10: 4.3 | E10: 51 Phạm Hồng Thái | F10: Hải Châu, Đà Nẵng | G10: Quán mỳ | H10: https://www.google.com/maps/search/?api=1&query=B%C3%A1nh%20M%C3%AC%20Qu%E1%BB%91c%20Doanh%20B%C3%A0%20%C4%90%E1%BB%A9c&query_place_id=ChIJgfgCUgAZQjERwkjkVnuEjcg | I10: 11
B11: Tổng nhóm | C11: =SUM(C2:C10) -> 8000
A13: Nhóm 8 | B13: Nhà Hàng Phì Lũ 1 | C13: 1035 | D13: 4.4 | E13: 225 Nguyễn Chí Thanh | F13: Hải Châu, Đà Nẵng | G13: Nhà hàng Trung Quốc | H13: https://www.google.com/maps/search/?api=1&query=Nh%C3%A0%20H%C3%A0ng%20Ph%C3%AC%20L%C5%A9%201&query_place_id=ChIJw-zBdzMYQjERNlbwU3SwOdc | I13: 1871
A14: Nhóm 8 | B14: Thai Market Restaurant - Trần Quốc Toản | C14: 1035 | D14: 4.5 | E14: 04 Trần Quốc Toản | F14: Hải Châu, Đà Nẵng | G14: Quán ăn tối | H14: https://www.google.com/maps/search/?api=1&query=Thai%20Market%20Restaurant%20-%20Tr%E1%BA%A7n%20Qu%E1%BB%91c%20To%E1%BA%A3n&query_place_id=ChIJKVfX8jIYQjER3mM7bO2HeqI | I14: 1859
A15: Nhóm 8 | B15: Highlands Coffee VTV8 | C15: 1035 | D15: 4.4 | E15: 258 Bạch Đằng | F15: Hai Chau, Da Nang | G15: Quán bar | H15: https://www.google.com/maps/search/?api=1&query=Highlands%20Coffee%20VTV8&query_place_id=ChIJr7zJYAkZQjERA0lYwQ-BpOk | I15: 1850
A16: Nhóm 8 | B16: Jollibee Đống Đa | C16: 1035 | D16: 4.7 | E16: 254 Đống Đa | F16: Hai Chau, Da Nang | G16: Tiệm bánh | H16: https://www.google.com/maps/search/?api=1&query=Jollibee%20%C4%90%E1%BB%91ng%20%C4%90a&query_place_id=ChIJRUl1tCoZQjER7SLSqKcTVgk | I16: 1777
A17: Nhóm 8 | B17: EZI - Đậm Đà Nẵng - 388 Đống Đa | C17: 1035 | D17: 4.6 | E17: 388 Đống Đa | F17: Hai Chau, Da Nang | G17: Quán trà sữa | H17: https://www.google.com/maps/search/?api=1&query=EZI%20-%20%C4%90%E1%BA%ADm%20%C4%90%C3%A0%20N%E1%BA%B5ng%20-%20388%20%C4%90%E1%BB%91ng%20%C4%90a&query_place_id=ChIJf-GHukcYQjERyQoRvi6SumQ | I17: 1732
A18: Nhóm 8 | B18: Phở Thìn Đà Nẵng | C18: 1035 | D18: 4.3 | E18: 60 Pasteur | F18: Hai Chau, Da Nang | G18: Quán nhậu | H18: https://www.google.com/maps/search/?api=1&query=Ph%E1%BB%9F%20Th%C3%ACn%20%C4%90%C3%A0%20N%E1%BA%B5ng&query_place_id=ChIJsRRKFxIZQjEReyTCrVbRXTs | I18: 1724
A19: Nhóm 8 | B19: Kết High | C19: 1035 | D19: 4.9 | E19: 200 Bạch Đằng | F19: Hai Chau, Da Nang | G19: Cocktail bar | H19: https://www.google.com/maps/search/?api=1&query=K%E1%BA%BFt%20High&query_place_id=ChIJh3XZqZgZQjERm2fg63ZDaRI | I19: 1658
A20: Nhóm 8 | B20: Túc Tắc Tea Đà Nẵng - Lê Đình Dương | C20: 714 | D20: 4.6 | E20: 70 Lê Đình Dương | F20: Hai Chau, Da Nang | G20: Trà sữa | H20: https://www.google.com/maps/search/?api=1&query=T%C3%BAc%20T%E1%BA%AFc%20Tea%20%C4%90%C3%A0%20N%E1%BA%B5ng%20-%20L%C3%AA%20%C4%90%C3%ACnh%20D%C6%B0%C6%A1ng&query_place_id=ChIJq2mJuZcZQjER2yeL4uflyxw | I20: 714
A21: Nhóm 8 | B21: Quán Dốc Sông Hàn | C21: 41 | D21: 5 | E21: 1b Lê Duẩn | F21: Hai Chau, Da Nang | G21: Quán bar | H21: https://www.google.com/maps/search/?api=1&query=Qu%C3%A1n%20D%E1%BB%91c%20S%C3%B4ng%20H%C3%A0n&query_place_id=ChIJuVYeSD4ZQjER1Tt9FFmhCV8 | I21: 41
B22: Tổng nhóm | C22: =SUM(C13:C21) -> 8000
A24: Nhóm 9 | B24: Cơm Tấm Đây | C24: 1035 | D24: 4.7 | E24: 5 Phạm Phú Thứ | F24: Hải Châu, Đà Nẵng | G24: Nhà hàng Việt Nam | H24: https://www.google.com/maps/search/?api=1&query=C%C6%A1m%20T%E1%BA%A5m%20%C4%90%C3%A2y&query_place_id=ChIJDW31iLoZQjERquS25NUtGw0 | I24: 1643
A25: Nhóm 9 | B25: Limoncello | C25: 1035 | D25: 4.5 | E25: 212 Trần Phú | F25: Hải Châu, Đà Nẵng | G25: Quán ăn tối | H25: https://www.google.com/maps/search/?api=1&query=Limoncello&query_place_id=ChIJMy-k-jIYQjERyab8z9yo1lU | I25: 1642
A26: Nhóm 9 | B26: I love Bánh mì 아이러브반미 | C26: 1035 | D26: 4.3 | E26: 100 Trần Phú | F26: Hải Châu, Đà Nẵng | G26: Quán phở | H26: https://www.google.com/maps/search/?api=1&query=I%20love%20B%C3%A1nh%20m%C3%AC%20%EC%95%84%EC%9D%B4%EB%9F%AC%EB%B8%8C%EB%B0%98%EB%AF%B8&query_place_id=ChIJkzlsHOUZQjERHQgzrQC-kG4 | I26: 1639
A27: Nhóm 9 | B27: Quán Huế Ngon | C27: 1035 | D27: 4.1 | E27: 65 Trần Quốc Toản | F27: Hải Châu, Đà Nẵng | G27: Nhà hàng hải sản | H27: https://www.google.com/maps/search/?api=1&query=Qu%C3%A1n%20Hu%E1%BA%BF%20Ngon&query_place_id=ChIJCXHPczMYQjERWvCLF3Hu_CY | I27: 1626
A28: Nhóm 9 | B28: IZAKAYA IDATEN | C28: 1035 | D28: 4.9 | E28: 32 Thái Phiên | F28: Hải Châu, Đà Nẵng | G28: Quán ăn tối | H28: https://www.google.com/maps/search/?api=1&query=IZAKAYA%20IDATEN&query_place_id=ChIJ0aAaX1YZQjERsrLCQVCoP74 | I28: 1619
A29: Nhóm 9 | B29: Phở Cù Hà Nội | C29: 1035 | D29: 4.6 | E29: 05 Trần Quốc Toản | F29: Hải Châu, Đà Nẵng | G29: Quán phở | H29: https://www.google.com/maps/search/?api=1&query=Ph%E1%BB%9F%20C%C3%B9%20H%C3%A0%20N%E1%BB%99i&query_place_id=ChIJZZV83B0ZQjER91WpMAjcoyk | I29: 1609
A30: Nhóm 9 | B30: Trình cà phê - VTV8 | C30: 1035 | D30: 4.8 | E30: 256 Bạch Đằng | F30: Hai Chau, Da Nang | G30: Quán cà phê | H30: https://www.google.com/maps/search/?api=1&query=Tr%C3%ACnh%20c%C3%A0%20ph%C3%AA%20-%20VTV8&query_place_id=ChIJayh2YEYZQjER3N9LNQu3nRI | I30: 1584
A31: Nhóm 9 | B31: Cửa Ngõ Café – Cửa Hàng Số 2 | C31: 713 | D31: 4.5 | E31: 102 Nguyễn Thị Minh Khai | F31: Hai Chau, Da Nang | G31: Quán sinh tố | H31: https://www.google.com/maps/search/?api=1&query=C%E1%BB%ADa%20Ng%C3%B5%20Caf%C3%A9%20%E2%80%93%20C%E1%BB%ADa%20H%C3%A0ng%20S%E1%BB%91%202&query_place_id=ChIJz2VlXIAZQjER9VRmwBZiBLI | I31: 713
A32: Nhóm 9 | B32: Quán ăn Tuấn Trọc | C32: 42 | D32: 5 | E32: 168 Đống Đa | F32: Hải Châu, Đà Nẵng | G32: Quán ăn | H32: https://www.google.com/maps/search/?api=1&query=Qu%C3%A1n%20%C4%83n%20Tu%E1%BA%A5n%20Tr%E1%BB%8Dc&query_place_id=ChIJf2o2WwAZQjERVLq7ZehzTCY | I32: 42
B33: Tổng nhóm | C33: =SUM(C24:C32) -> 8000
A35: Nhóm 16 | B35: Nhà hàng Làn Gió | C35: 1035 | D35: 4.7 | E35: 169 Trần Phú | F35: Hải Châu, Đà Nẵng | G35: Nhà hàng buffet | H35: https://www.google.com/maps/search/?api=1&query=Nh%C3%A0%20h%C3%A0ng%20L%C3%A0n%20Gi%C3%B3&query_place_id=ChIJNRSpo9EZQjERliMnRlTXtFc | I35: 1246
A36: Nhóm 16 | B36: Quán Cô Hồng - Gỏi Cá Nam Ô | C36: 1035 | D36: 4.5 | E36: 38 Lê Hồng Phong | F36: Hải Châu, Đà Nẵng | G36: Nhà hàng hải sản | H36: https://www.google.com/maps/search/?api=1&query=Qu%C3%A1n%20C%C3%B4%20H%E1%BB%93ng%20-%20G%E1%BB%8Fi%20C%C3%A1%20Nam%20%C3%94&query_place_id=ChIJQ7Wm3ssZQjERC5aR2l8cnno | I36: 1244
A37: Nhóm 16 | B37: Alluvia Chocolate 172 Tran Phu | C37: 1035 | D37: 5 | E37: 172 Trần Phú | F37: Hai Chau, Da Nang | G37: Tiệm bánh | H37: https://www.google.com/maps/search/?api=1&query=Alluvia%20Chocolate%20172%20Tran%20Phu&query_place_id=ChIJ-1l4aSMZQjERLwivCCHlDBU | I37: 1242
A38: Nhóm 16 | B38: Mikado Sushi Indochina Riverside Da Nang | C38: 1035 | D38: 4.6 | E38: 01 Phan Đình Phùng | F38: Hải Châu, Đà Nẵng | G38: Nhà hàng buffet | H38: https://www.google.com/maps/search/?api=1&query=Mikado%20Sushi%20Indochina%20Riverside%20Da%20Nang&query_place_id=ChIJu0MjQwAZQjER6D4wxqkxTJA | I38: 1231
A39: Nhóm 16 | B39: Gé Cafe | C39: 1035 | D39: 4.3 | E39: 24 Lê Hồng Phong | F39: Hai Chau, Da Nang | G39: Quán cà phê | H39: https://www.google.com/maps/search/?api=1&query=G%C3%A9%20Cafe&query_place_id=ChIJbdw0bPoZQjERz0BEiJv3dkY | I39: 1218
A40: Nhóm 16 | B40: Cà Phê Muối Huế 3 - NCF Trần Phú | C40: 1035 | D40: 4.6 | E40: 254 Trần Phú | F40: Hai Chau, Da Nang | G40: Quán bar | H40: https://www.google.com/maps/search/?api=1&query=C%C3%A0%20Ph%C3%AA%20Mu%E1%BB%91i%20Hu%E1%BA%BF%203%20-%20NCF%20Tr%E1%BA%A7n%20Ph%C3%BA&query_place_id=ChIJ_5NQ-bkZQjERIMvo3zh7Ipw | I40: 1213
A41: Nhóm 16 | B41: Phở Hub - Halal Vietnamese Cuisine | C41: 1035 | D41: 4.8 | E41: 181 Nguyễn Chí Thanh | F41: Hải Châu, Đà Nẵng | G41: Quán mỳ | H41: https://www.google.com/maps/search/?api=1&query=Ph%E1%BB%9F%20Hub%20-%20Halal%20Vietnamese%20Cuisine&query_place_id=ChIJU5ubXpAZQjERSVCg35N7eJA | I41: 1184
A42: Nhóm 16 | B42: Hủ Tiếu Mực | C42: 686 | D42: 4.3 | E42: 15 Lê Hồng Phong | F42: Hải Châu, Đà Nẵng | G42: Quán ăn tối | H42: https://www.google.com/maps/search/?api=1&query=H%E1%BB%A7%20Ti%E1%BA%BFu%20M%E1%BB%B1c&query_place_id=ChIJQ3mJfa8ZQjERIuvEwSIFc4E | I42: 686
A43: Nhóm 16 | B43: Quán Bà Hoành - Mỳ quảng & Bún Bò | C43: 69 | D43: 4.3 | E43: 152 Nguyễn Hoàng | F43: Thanh Khe, Da Nang | G43: Quán bánh mì | H43: https://www.google.com/maps/search/?api=1&query=Qu%C3%A1n%20B%C3%A0%20Ho%C3%A0nh%20-%20M%E1%BB%B3%20qu%E1%BA%A3ng%20%26%20B%C3%BAn%20B%C3%B2&query_place_id=ChIJacC6f7UZQjER86X3L47l_HI | I43: 69
B44: Tổng nhóm | C44: =SUM(C35:C43) -> 8000
A46: Nhóm 17 | B46: Al Fresco's Trần Phú | C46: 1035 | D46: 4.2 | E46: 184 Trần Phú | F46: Hai Chau, Da Nang | G46: Beer club | H46: https://www.google.com/maps/search/?api=1&query=Al%20Fresco's%20Tr%E1%BA%A7n%20Ph%C3%BA&query_place_id=ChIJKSFfiTIYQjERc_NIt_u2Htc | I46: 1174
A47: Nhóm 17 | B47: Cafeholic Coffee | C47: 1035 | D47: 4.7 | E47: 52 Lê Lợi | F47: Hai Chau, Da Nang | G47: Coffee | H47: https://www.google.com/maps/search/?api=1&query=Cafeholic%20Coffee&query_place_id=ChIJs4D2VRsZQjERWU-okFEBjSM | I47: 1172
A48: Nhóm 17 | B48: TÂY HỒ QUÁN - Bún chả Hà Nội -Bún Riêu Cua Ốc | C48: 1035 | D48: 4.9 | E48: 86 Quang Trung | F48: Hải Châu, Đà Nẵng | G48: Quán bún | H48: https://www.google.com/maps/search/?api=1&query=T%C3%82Y%20H%E1%BB%92%20QU%C3%81N%20-%20B%C3%BAn%20ch%E1%BA%A3%20H%C3%A0%20N%E1%BB%99i%20-B%C3%BAn%20Ri%C3%AAu%20Cua%20%E1%BB%90c&query_place_id=ChIJ2w0OhDcZQjER7tIUWXw34KQ | I48: 1142
A49: Nhóm 17 | B49: PHỞ BẮC 63 | C49: 1035 | D49: 4.1 | E49: 203 Đống Đa | F49: Hai Chau, Da Nang | G49: Quán nhậu | H49: https://www.google.com/maps/search/?api=1&query=PH%E1%BB%9E%20B%E1%BA%AEC%2063&query_place_id=ChIJk6TIIzgYQjERTS1_C94qwUA | I49: 1113
A50: Nhóm 17 | B50: Quán ăn Dim Sum | C50: 1035 | D50: 4.4 | E50: 45a Ng. Gia Tự | F50: Hải Châu, Đà Nẵng | G50: Quán ăn | H50: https://www.google.com/maps/search/?api=1&query=Qu%C3%A1n%20%C4%83n%20Dim%20Sum&query_place_id=ChIJo8JCMDQYQjER95NU9lh9qfw | I50: 1108
A51: Nhóm 17 | B51: Tâm Ngon Garden Đà Nẵng | C51: 1035 | D51: 4.9 | E51: 66-68 Trần Quốc Toản | F51: Hải Châu, Đà Nẵng | G51: Quán phở | H51: https://www.google.com/maps/search/?api=1&query=T%C3%A2m%20Ngon%20Garden%20%C4%90%C3%A0%20N%E1%BA%B5ng&query_place_id=ChIJF9KrROkXQjERT9vRCFoa3-s | I51: 1106
A52: Nhóm 17 | B52: Mỳ Quảng Bà Mua | C52: 1035 | D52: 3.8 | E52: 19 Trần Bình Trọng | F52: Hai Chau, Da Nang | G52: Quán bar | H52: https://www.google.com/maps/search/?api=1&query=M%E1%BB%B3%20Qu%E1%BA%A3ng%20B%C3%A0%20Mua&query_place_id=ChIJcS1UmjQYQjER1fpZXq5x4Ds | I52: 1100
A53: Nhóm 17 | B53: Bún chả cá Bà Hoa | C53: 684 | D53: 4.2 | E53: 27 Lê Hồng Phong | F53: Hải Châu, Đà Nẵng | G53: Quán ăn tối | H53: https://www.google.com/maps/search/?api=1&query=B%C3%BAn%20ch%E1%BA%A3%20c%C3%A1%20B%C3%A0%20Hoa&query_place_id=ChIJO0y6zMwZQjERPpCdjFDoGqg | I53: 684
A54: Nhóm 17 | B54: Quán nhậu Tiến Thành | C54: 71 | D54: 4 | E54: 207 Trần Phú | F54: Hải Châu, Đà Nẵng | G54: Quán mỳ | H54: https://www.google.com/maps/search/?api=1&query=Qu%C3%A1n%20nh%E1%BA%ADu%20Ti%E1%BA%BFn%20Th%C3%A0nh&query_place_id=ChIJoxFc2zIYQjERW0tWrlfqsFg | I54: 71
B55: Tổng nhóm | C55: =SUM(C46:C54) -> 8000
A57: Nhóm 24 | B57: Luu.sweety | C57: 643 | D57: 4.8 | E57: 63 Phan Châu Trinh | F57: Hai Chau, Da Nang | G57: Tiệm bánh | H57: https://www.google.com/maps/search/?api=1&query=Luu.sweety&query_place_id=ChIJi9PrJgAZQjERE9N5owFiQiM | I57: 643
A58: Nhóm 24 | B58: Pi Thai - Hủ Tiếu Thái Lan | C58: 642 | D58: 4.5 | E58: Nguyễn Văn Linh/33 Bình Hiên | F58: Hải Châu, Đà Nẵng | G58: restaurant | H58: https://www.google.com/maps/search/?api=1&query=Pi%20Thai%20-%20H%E1%BB%A7%20Ti%E1%BA%BFu%20Th%C3%A1i%20Lan&query_place_id=ChIJBw5CaS8ZQjERVjC4VfpnffE | I58: 642
A59: Nhóm 24 | B59: Chào Bà - Bún Chả Hà Nội Xưa | C59: 638 | D59: 4.4 | E59: 98 Yên Bái | F59: Hải Châu, Đà Nẵng | G59: Nhà hàng hải sản | H59: https://www.google.com/maps/search/?api=1&query=Ch%C3%A0o%20B%C3%A0%20-%20B%C3%BAn%20Ch%E1%BA%A3%20H%C3%A0%20N%E1%BB%99i%20X%C6%B0a&query_place_id=ChIJpeJe9usZQjERr1clbE1M92g | I59: 638
A60: Nhóm 24 | B60: Đông Đô cà phê | C60: 638 | D60: 4.7 | E60: 22/4 Lê Đình Dương | F60: Hai Chau, Da Nang | G60: Cửa hàng bánh ngọt | H60: https://www.google.com/maps/search/?api=1&query=%C4%90%C3%B4ng%20%C4%90%C3%B4%20c%C3%A0%20ph%C3%AA&query_place_id=ChIJyQHnm90ZQjERpKEIMCLCYcQ | I60: 638
A61: Nhóm 24 | B61: PY's Fúd | C61: 635 | D61: 4.7 | E61: 29 Nguyễn Chí Thanh | F61: Hải Châu, Đà Nẵng | G61: Nhà hàng Hàn Quốc | H61: https://www.google.com/maps/search/?api=1&query=PY's%20F%C3%BAd&query_place_id=ChIJ2ZrbdksZQjERcTUA3xKVfAc | I61: 635
A62: Nhóm 24 | B62: Courtyard by Marriott Danang Han River | C62: 633 | D62: 4.3 | E62: 58 Bạch Đằng | F62: Hai Chau, Da Nang | G62: Quán bar | H62: https://www.google.com/maps/search/?api=1&query=Courtyard%20by%20Marriott%20Danang%20Han%20River&query_place_id=ChIJ59whU3QZQjERJcF_NKFGYnQ | I62: 633
A63: Nhóm 24 | B63: Tàu Rồng Sông Hàn | C63: 631 | D63: 4 | E63: Bạch Đằng | F63: Hai Chau, Da Nang | G63: Quán nhậu | H63: https://www.google.com/maps/search/?api=1&query=T%C3%A0u%20R%E1%BB%93ng%20S%C3%B4ng%20H%C3%A0n&query_place_id=ChIJnW6SIbAZQjERCKgAt0bxwWg | I63: 631
A64: Nhóm 24 | B64: ANGEL LOUNGE | C64: 625 | D64: 5 | E64: 37 Lý Tự Trọng | F64: Hai Chau, Da Nang | G64: Lounge bar | H64: https://www.google.com/maps/search/?api=1&query=ANGEL%20LOUNGE&query_place_id=ChIJW5KDTQAZQjERJXJQMoz2YJo | I64: 625
A65: Nhóm 24 | B65: Phở 29 - Ăn Thôi - 다낭 쌀국수 맛집 | C65: 621 | D65: 4.5 | E65: 06B Trần Quốc Toản | F65: Hải Châu, Đà Nẵng | G65: Nhà hàng hải sản | H65: https://www.google.com/maps/search/?api=1&query=Ph%E1%BB%9F%2029%20-%20%C4%82n%20Th%C3%B4i%20-%20%EB%8B%A4%EB%82%AD%20%EC%8C%80%EA%B5%AD%EC%88%98%20%EB%A7%9B%EC%A7%91&query_place_id=ChIJJQJ6jd8ZQjERy05iRaclHdM | I65: 621
A66: Nhóm 24 | B66: Dua Ben Tre 190 | C66: 617 | D66: 4.1 | E66: 190 Bạch Đằng | F66: Hai Chau, Da Nang | G66: Tiệm bánh | H66: https://www.google.com/maps/search/?api=1&query=Dua%20Ben%20Tre%20190&query_place_id=ChIJP97Tv5IZQjERyhO3If-jle0 | I66: 617
A67: Nhóm 24 | B67: Bánh bèo Tâm | C67: 617 | D67: 4.2 | E67: 291 Nguyễn Chí Thanh | F67: Hai Chau, Da Nang | G67: Tiệm bánh | H67: https://www.google.com/maps/search/?api=1&query=B%C3%A1nh%20b%C3%A8o%20T%C3%A2m&query_place_id=ChIJc-7jUTMYQjERwS8-Cc0xcds | I67: 617
A68: Nhóm 24 | B68: Cơm Tấm Ốp Lết 1940 | C68: 617 | D68: 4.5 | E68: 89 Yên Bái | F68: Hải Châu, Đà Nẵng | G68: Quán ăn tối | H68: https://www.google.com/maps/search/?api=1&query=C%C6%A1m%20T%E1%BA%A5m%20%E1%BB%90p%20L%E1%BA%BFt%201940&query_place_id=ChIJH2RERzAZQjERKgRHwIPShtM | I68: 617
... A70: Nhóm 24 | B70: Milk Lab | C70: 1 | D70: 5 | E70: 18/12 Ông Ích Khiêm | F70: Hai Chau, Da Nang | G70: Coffee | H70: https://www.google.com/maps/search/?api=1&query=Milk%20Lab&query_place_id=ChIJE7riXQAZQjER1WKYtoEJgHg | I70: 1
B71: Tổng nhóm | C71: =SUM(C57:C70) -> 8000
A73: Nhóm 25 | B73: Le Bambino French Restaurant | C73: 613 | D73: 4.3 | E73: 122/11 Quang Trung | F73: Hai Chau, Da Nang | G73: Wine bar | H73: https://www.google.com/maps/search/?api=1&query=Le%20Bambino%20French%20Restaurant&query_place_id=ChIJv5ziezoYQjERwD3iyIbYfVQ | I73: 613
A74: Nhóm 25 | B74: The Pizza Company Đống Đa - Đà Nẵng | C74: 604 | D74: 4.9 | E74: 147 - 149, Đống Đa | F74: Hai Chau, Da Nang | G74: Quán pizza | H74: https://www.google.com/maps/search/?api=1&query=The%20Pizza%20Company%20%C4%90%E1%BB%91ng%20%C4%90a%20-%20%C4%90%C3%A0%20N%E1%BA%B5ng&query_place_id=ChIJoxuqby0ZQjERUTrPfnSb-y8 | I74: 604
A75: Nhóm 25 | B75: Highlands Coffee | C75: 603 | D75: 4.2 | E75: 145 Quang Trung | F75: Hai Chau, Da Nang | G75: Cafe | H75: https://www.google.com/maps/search/?api=1&query=Highlands%20Coffee&query_place_id=ChIJM1OVpdoZQjERct4DjcPXTLg | I75: 603
A76: Nhóm 25 | B76: Mixue 235 Đống Đa | C76: 600 | D76: 4.6 | E76: 235 Đống Đa | F76: Hai Chau, Da Nang | G76: Quán trà sữa | H76: https://www.google.com/maps/search/?api=1&query=Mixue%20235%20%C4%90%E1%BB%91ng%20%C4%90a&query_place_id=ChIJTSht1qoZQjERXGUdAgUjN2k | I76: 600
A77: Nhóm 25 | B77: Bông Food & Drink | C77: 596 | D77: 4.1 | E77: 123 Nguyễn Thị Minh Khai | F77: Hai Chau, Da Nang | G77: Trà sữa | H77: https://www.google.com/maps/search/?api=1&query=B%C3%B4ng%20Food%20%26%20Drink&query_place_id=ChIJk4R3efEZQjERUKYTVeFT8vI | I77: 596
A78: Nhóm 25 | B78: Sushi World | C78: 586 | D78: 4.3 | E78: 10 Phan Bội Châu | F78: Hai Chau, Da Nang | G78: Wine bar | H78: https://www.google.com/maps/search/?api=1&query=Sushi%20World&query_place_id=ChIJGblG9TsYQjERtmcp0oBaD4M | I78: 586
A79: Nhóm 25 | B79: Bánh Xèo Làng | C79: 586 | D79: 4.9 | E79: 58 Trần Quốc Toản | F79: Hai Chau, Da Nang | G79: Quán nhậu | H79: https://www.google.com/maps/search/?api=1&query=B%C3%A1nh%20X%C3%A8o%20L%C3%A0ng&query_place_id=ChIJ48EeJQAZQjERIe-_Dcu4kno | I79: 586
A80: Nhóm 25 | B80: Mì Cay Kitachi 144 Ông Ích Khiêm, Đà Nẵng | C80: 585 | D80: 4 | E80: 144 Ông Ích Khiêm | F80: Thanh Khê, Đà Nẵng | G80: Quán mỳ | H80: https://www.google.com/maps/search/?api=1&query=M%C3%AC%20Cay%20Kitachi%20144%20%C3%94ng%20%C3%8Dch%20Khi%C3%AAm%2C%20%C4%90%C3%A0%20N%E1%BA%B5ng&query_place_id=ChIJNfGf6dgZQjERdaR7xenR9GE | I80: 585
A81: Nhóm 25 | B81: Nhà hàng Forever | C81: 582 | D81: 3.9 | E81: 44 Phan Đình Phùng | F81: Hải Châu, Đà Nẵng | G81: Quán ăn tối | H81: https://www.google.com/maps/search/?api=1&query=Nh%C3%A0%20h%C3%A0ng%20Forever&query_place_id=ChIJ2eEXaTEYQjER4iFzHUaOVLo | I81: 582
A82: Nhóm 25 | B82: Bánh cuốn Tiến Hưng | C82: 582 | D82: 4.1 | E82: 190 Trần Phú | F82: Hai Chau, Da Nang | G82: Tiệm bánh | H82: https://www.google.com/maps/search/?api=1&query=B%C3%A1nh%20cu%E1%BB%91n%20Ti%E1%BA%BFn%20H%C6%B0ng&query_place_id=ChIJxe173DIYQjERHexCCn8zrAo | I82: 582
A83: Nhóm 25 | B83: Madam Võ ĐN - Tiệm thịt nướng Hongkong | C83: 579 | D83: 4.5 | E83: 74 Nguyễn Chí Thanh | F83: Hải Châu, Đà Nẵng | G83: Nhà hàng buffet | H83: https://www.google.com/maps/search/?api=1&query=Madam%20V%C3%B5%20%C4%90N%20-%20Ti%E1%BB%87m%20th%E1%BB%8Bt%20n%C6%B0%E1%BB%9Bng%20Hongkong&query_place_id=ChIJFc9qaPMZQjERaKlJMtRVWVY | I83: 579
A84: Nhóm 25 | B84: Quán Đông Phương | C84: 575 | D84: 3.8 | E84: 255 Nguyễn Tất Thành | F84: Hải Châu, Đà Nẵng | G84: Quán ăn | H84: https://www.google.com/maps/search/?api=1&query=Qu%C3%A1n%20%C4%90%C3%B4ng%20Ph%C6%B0%C6%A1ng&query_place_id=ChIJ5-Gd90YYQjERcifVB8XnGJQ | I84: 575
... A86: Nhóm 25 | B86: Cộng Cà Phê | C86: 335 | D86: 3.9 | E86: 39-41 Nguyễn Thái Học | F86: Hai Chau, Da Nang | G86: Quán cà phê | H86: https://www.google.com/maps/search/?api=1&query=C%E1%BB%99ng%20C%C3%A0%20Ph%C3%AA&query_place_id=ChIJbQQgOUwZQjERq_nJzgdkcQk | I86: 335
B87: Tổng nhóm | C87: =SUM(C73:C86) -> 8000
A89: Nhóm 32 | B89: City High Dining | C89: 314 | D89: 4.8 | E89: Đối diện 27/9, Ng. Gia Tự | F89: Hai Chau, Da Nang | G89: Wine bar | H89: https://www.google.com/maps/search/?api=1&query=City%20High%20Dining&query_place_id=ChIJ0ZHggqoZQjER5HM52xEIGQI | I89: 314
A90: Nhóm 32 | B90: Ichiban sushi da nang | C90: 310 | D90: 4.8 | E90: 206 Trần Phú | F90: Hải Châu, Đà Nẵng | G90: Nhà hàng Nhật Bản | H90: https://www.google.com/maps/search/?api=1&query=Ichiban%20sushi%20da%20nang&query_place_id=ChIJI0gbNhwZQjERFi3N4pZx6N0 | I90: 310
A91: Nhóm 32 | B91: Bánh canh NGA | C91: 309 | D91: 4.7 | E91: 78c Nguyễn Chí Thanh | F91: Hai Chau, Da Nang | G91: Quán bar | H91: https://www.google.com/maps/search/?api=1&query=B%C3%A1nh%20canh%20NGA&query_place_id=ChIJg0KHpGMZQjERmxae3ZO3xDw | I91: 309
A92: Nhóm 32 | B92: Thinh Bakery | C92: 308 | D92: 4.9 | E92: 123 Nguyễn Chí Thanh | F92: Hai Chau, Da Nang | G92: Bánh mỳ | H92: https://www.google.com/maps/search/?api=1&query=Thinh%20Bakery&query_place_id=ChIJpX3uvLYZQjERvYK3sTYOkz0 | I92: 308
A93: Nhóm 32 | B93: KINTER COFFEE | C93: 308 | D93: 4.5 | E93: 12 Cao Thắng | F93: Hai Chau, Da Nang | G93: Coffee | H93: https://www.google.com/maps/search/?api=1&query=KINTER%20COFFEE&query_place_id=ChIJrQ4PC84ZQjERFWMJEF7OCj8 | I93: 308
A94: Nhóm 32 | B94: Mada Bistro | C94: 305 | D94: 4.8 | E94: Quang Trung/36/19 Đ. Thành Điện Hải | F94: Hai Chau, Da Nang | G94: Quán nhậu | H94: https://www.google.com/maps/search/?api=1&query=Mada%20Bistro&query_place_id=ChIJgU-gkWoZQjERaJjZwBD-q2g | I94: 305
A95: Nhóm 32 | B95: Mì Quảng Đà Nẵng - Mỳ Quảng Bà Mua - Đặc Sản Đà Nẵng | C95: 305 | D95: 3.9 | E95: 231 Đống Đa | F95: Hải Châu, Đà Nẵng | G95: Quán mỳ | H95: https://www.google.com/maps/search/?api=1&query=M%C3%AC%20Qu%E1%BA%A3ng%20%C4%90%C3%A0%20N%E1%BA%B5ng%20-%20M%E1%BB%B3%20Qu%E1%BA%A3ng%20B%C3%A0%20Mua%20-%20%C4%90%E1%BA%B7c%20S%E1%BA%A3n%20%C4%90%C3%A0%20N%E1%BA%B5ng&query_place_id=ChIJg322TjgYQjERSS9XXYj_xME | I95: 305
A96: Nhóm 32 | B96: Xôi, Bún măng gà bà Vui | C96: 303 | D96: 4.6 | E96: 55 Lê Hồng Phong | F96: Hải Châu, Đà Nẵng | G96: Nhà hàng hải sản | H96: https://www.google.com/maps/search/?api=1&query=X%C3%B4i%2C%20B%C3%BAn%20m%C4%83ng%20g%C3%A0%20b%C3%A0%20Vui&query_place_id=ChIJ3364sswZQjERd8RaGXqHqCc | I96: 303
A97: Nhóm 32 | B97: Magicha.Zenbar ( Matcha / 抹茶 / 말차 ) | C97: 301 | D97: 4.6 | E97: 75/2 Lê Hồng Phong | F97: Hai Chau, Da Nang | G97: Quán bar | H97: https://www.google.com/maps/search/?api=1&query=Magicha.Zenbar%20(%20Matcha%20%2F%20%E6%8A%B9%E8%8C%B6%20%2F%20%EB%A7%90%EC%B0%A8%20)&query_place_id=ChIJqQfwGRIZQjERQBXKZobv_fU | I97: 301
A98: Nhóm 32 | B98: Quán Bánh Xèo Miền Trung Bà Tình | C98: 299 | D98: 4.6 | E98: 280 Hoàng Diệu | F98: Hải Châu, Đà Nẵng | G98: Quán ăn | H98: https://www.google.com/maps/search/?api=1&query=Qu%C3%A1n%20B%C3%A1nh%20X%C3%A8o%20Mi%E1%BB%81n%20Trung%20B%C3%A0%20T%C3%ACnh&query_place_id=ChIJjzeKSE0YQjERI8FF2cWF3NY | I98: 299
A99: Nhóm 32 | B99: Mì Quảng Hồng Vân | C99: 299 | D99: 4.4 | E99: 59C Lê Hồng Phong | F99: Hải Châu, Đà Nẵng | G99: Quán ăn tối | H99: https://www.google.com/maps/search/?api=1&query=M%C3%AC%20Qu%E1%BA%A3ng%20H%E1%BB%93ng%20V%C3%A2n&query_place_id=ChIJmSUtrcwZQjERKAbtHFEaR0w | I99: 299
A100: Nhóm 32 | B100: Cơm tấm Vân Hương | C100: 298 | D100: 4.4 | E100: 31 Nguyễn Thị Minh Khai | F100: Hải Châu, Đà Nẵng | G100: Quán ăn trưa | H100: https://www.google.com/maps/search/?api=1&query=C%C6%A1m%20t%E1%BA%A5m%20V%C3%A2n%20H%C6%B0%C6%A1ng&query_place_id=ChIJbRnyZTcYQjERac_y9FT93hQ | I100: 298
... A116: Nhóm 32 | B116: Bún chả cá Tam giác | C116: 37 | D116: 4.2 | E116: 166 Hải Phòng | F116: Thanh Khê, Đà Nẵng | G116: Quán ăn sáng | H116: https://www.google.com/maps/search/?api=1&query=B%C3%BAn%20ch%E1%BA%A3%20c%C3%A1%20Tam%20gi%C3%A1c&query_place_id=ChIJm1LBHgAZQjEREt-0Tiaujmk | I116: 37
B117: Tổng nhóm | C117: =SUM(C89:C116) -> 8000
A119: Nhóm 33 | B119: Khâu.cà phê | C119: 275 | D119: 4.4 | E119: 75/18 Lê Hồng Phong | F119: Hai Chau, Da Nang | G119: Quán bar | H119: https://www.google.com/maps/search/?api=1&query=Kh%C3%A2u.c%C3%A0%20ph%C3%AA&query_place_id=ChIJ-wZaJ2QZQjERhmDzz7BMz5g | I119: 275
A120: Nhóm 33 | B120: Nông - Lẩu & Cuốn - Chuyên lẩu khổ qua rừng và món cuốn | C120: 274 | D120: 4.9 | E120: 74A Nguyễn Thị Minh Khai | F120: Hải Châu, Đà Nẵng | G120: Quán ăn tối | H120: https://www.google.com/maps/search/?api=1&query=N%C3%B4ng%20-%20L%E1%BA%A9u%20%26%20Cu%E1%BB%91n%20-%20Chuy%C3%AAn%20l%E1%BA%A9u%20kh%E1%BB%95%20qua%20r%E1%BB%ABng%20v%C3%A0%20m%C3%B3n%20cu%E1%BB%91n&query_place_id=ChIJd0cyPgAZQjER_NuUu1XZHcI | I120: 274
A121: Nhóm 33 | B121: Nam Hin Restaurant(Vietnamese Cuisine) - Han Market | C121: 272 | D121: 4.9 | E121: 70 Hùng Vương | F121: Hải Châu, Đà Nẵng | G121: Nhà hàng Việt Nam | H121: https://www.google.com/maps/search/?api=1&query=Nam%20Hin%20Restaurant(Vietnamese%20Cuisine)%20-%20Han%20Market&query_place_id=ChIJWc5Xi5sZQjERVnblMm4HZKY | I121: 272
A122: Nhóm 33 | B122: Min Sushi Đà Nẵng | C122: 272 | D122: 4.8 | E122: 48 Đ. 2 Tháng 9 | F122: Hải Châu, Đà Nẵng | G122: restaurant | H122: https://www.google.com/maps/search/?api=1&query=Min%20Sushi%20%C4%90%C3%A0%20N%E1%BA%B5ng&query_place_id=ChIJEY8MfgAZQjERPny8kybcYmw | I122: 272
A123: Nhóm 33 | B123: The Dude Bar | C123: 271 | D123: 4.4 | E123: 210 Bạch Đằng | F123: Hai Chau, Da Nang | G123: Club đêm | H123: https://www.google.com/maps/search/?api=1&query=The%20Dude%20Bar&query_place_id=ChIJs2-MEdgZQjERS7gaqVXkLCc | I123: 271
A124: Nhóm 33 | B124: Gỏi cá Nam Ô A. Sinh | C124: 270 | D124: 4.8 | E124: 130 Huỳnh Thúc Kháng | F124: Hai Chau, Da Nang | G124: Quán nhậu | H124: https://www.google.com/maps/search/?api=1&query=G%E1%BB%8Fi%20c%C3%A1%20Nam%20%C3%94%20A.%20Sinh&query_place_id=ChIJGUEIQ2YbQjER8Qk002Z5cEY | I124: 270
A125: Nhóm 33 | B125: drinktalk bar | C125: 269 | D125: 5 | E125: 164 Triệu Nữ Vương | F125: Hai Chau, Da Nang | G125: Cocktail bar | H125: https://www.google.com/maps/search/?api=1&query=drinktalk%20bar&query_place_id=ChIJ3xIDDQAZQjERZ5guoEhBEw4 | I125: 269
...

Sheet Trân
A1: Nhóm | B1: title | C1: reviewsCount (max 1035) | D1: totalScore | E1: street | F1: state | G1: searchString | H1: url | I1: reviewsCount gốc
A2: Nhóm 2 | B2: Trình cà phê | C2: 1035 | D2: 4.8 | E2: 25 Phạm Hồng Thái | F2: Hai Chau, Da Nang | G2: Quán cà phê | H2: https://www.google.com/maps/search/?api=1&query=Tr%C3%ACnh%20c%C3%A0%20ph%C3%AA&query_place_id=ChIJ2eFWbrcXQjERkMR0z_5VhM0 | I2: 7814
A3: Nhóm 2 | B3: Cô Ba Phở bò | C3: 1035 | D3: 4.7 | E3: 154 Bạch Đằng | F3: Hải Châu, Đà Nẵng | G3: Quán phở | H3: https://www.google.com/maps/search/?api=1&query=C%C3%B4%20Ba%20Ph%E1%BB%9F%20b%C3%B2&query_place_id=ChIJQYGTw4MZQjER9-WZcXZUfAM | I3: 6729
A4: Nhóm 2 | B4: UGANE | C4: 1035 | D4: 4.9 | E4: 181 Trần Phú | F4: Hai Chau, Da Nang | G4: Tiệm bánh | H4: https://www.google.com/maps/search/?api=1&query=UGANE&query_place_id=ChIJlcQ5nxwZQjERKZyFr1rNcCw | I4: 6594
A5: Nhóm 2 | B5: Nhà hàng NHÀ BẾP CHỢ HÀN | C5: 1035 | D5: 4.7 | E5: 22 Hùng Vương | F5: Hải Châu, Đà Nẵng | G5: Nhà hàng | H5: https://www.google.com/maps/search/?api=1&query=Nh%C3%A0%20h%C3%A0ng%20NH%C3%80%20B%E1%BA%BEP%20CH%E1%BB%A2%20H%C3%80N&query_place_id=ChIJP1Uz6i0ZQjERfy-rpM1cGWc | I5: 5997
A6: Nhóm 2 | B6: UMEYAKI - BBQ BUFFET | C6: 1035 | D6: 4.9 | E6: 26 Quang Trung | F6: Hải Châu, Đà Nẵng | G6: Nhà hàng buffet | H6: https://www.google.com/maps/search/?api=1&query=UMEYAKI%20-%20BBQ%20BUFFET&query_place_id=ChIJi_oeVgAZQjERvZH3PK8qRLA | I6: 4789
A7: Nhóm 2 | B7: MAAZI | C7: 1035 | D7: 4.8 | E7: 264 Trần Phú | F7: Hải Châu, Đà Nẵng | G7: restaurant | H7: https://www.google.com/maps/search/?api=1&query=MAAZI&query_place_id=ChIJqaQoXYMZQjERX_QzVEAZr_Q | I7: 4721
A8: Nhóm 2 | B8: Quán Phở Hồng | C8: 1035 | D8: 4.3 | E8: 10 Lý Tự Trọng | F8: Hai Chau, Da Nang | G8: Pub | H8: https://www.google.com/maps/search/?api=1&query=Qu%C3%A1n%20Ph%E1%BB%9F%20H%E1%BB%93ng&query_place_id=ChIJ5crNSwAZQjER1FLL3WSTID8 | I8: 4706
A9: Nhóm 2 | B9: Sangha - Vegetarian Restaurant | C9: 740 | D9: 4.5 | E9: 84 Hoàng Văn Thụ | F9: Hải Châu, Đà Nẵng | G9: restaurant | H9: https://www.google.com/maps/search/?api=1&query=Sangha%20-%20Vegetarian%20Restaurant&query_place_id=ChIJqwoK1BwZQjERSG9mG5m__eI | I9: 740
A10: Nhóm 2 | B10: Adam Cafe | C10: 15 | D10: 3.5 | E10: 114 Phan Châu Trinh | F10: Hai Chau, Da Nang | G10: Quán cà phê | H10: https://www.google.com/maps/search/?api=1&query=Adam%20Cafe&query_place_id=ChIJqTXNurQZQjERWBP_4tHP6Bo | I10: 15
B11: Tổng nhóm | C11: =SUM(C2:C10) -> 8000
A13: Nhóm 7 | B13: Bánh mì Cô Tiên | C13: 1035 | D13: 4.2 | E13: Kiệt 80/10 Trần Phú | F13: Hải Châu, Đà Nẵng | G13: Quán mỳ | H13: https://www.google.com/maps/search/?api=1&query=B%C3%A1nh%20m%C3%AC%20C%C3%B4%20Ti%C3%AAn&query_place_id=ChIJvXHUrV0ZQjERoXiEbJBkSoc | I13: 2077
A14: Nhóm 7 | B14: BREWHAHA Central - Local Craft Beer House | C14: 1035 | D14: 4.6 | E14: 16 Thái Phiên | F14: Hai Chau, Da Nang | G14: Beer club | H14: https://www.google.com/maps/search/?api=1&query=BREWHAHA%20Central%20-%20Local%20Craft%20Beer%20House&query_place_id=ChIJa333v4gPQjERdo78iUdIOS0 | I14: 2008
A15: Nhóm 7 | B15: Totoro Nướng & Sushi - Quán Nướng, Sushi Đà Nẵng | C15: 1035 | D15: 4.9 | E15: 287 Nguyễn Chí Thanh | F15: Hải Châu, Đà Nẵng | G15: Quán ăn tối | H15: https://www.google.com/maps/search/?api=1&query=Totoro%20N%C6%B0%E1%BB%9Bng%20%26%20Sushi%20-%20Qu%C3%A1n%20N%C6%B0%E1%BB%9Bng%2C%20Sushi%20%C4%90%C3%A0%20N%E1%BA%B5ng&query_place_id=ChIJxZsivFIZQjERLFjdCkk-uHg | I15: 1998
A16: Nhóm 7 | B16: LUK LAK | C16: 1035 | D16: 4.6 | E16: 28 Bạch Đằng | F16: Hai Chau, Da Nang | G16: Pub | H16: https://www.google.com/maps/search/?api=1&query=LUK%20LAK&query_place_id=ChIJUWBNGo0ZQjERJDLv-2XGwe8 | I16: 1967
A17: Nhóm 7 | B17: NAM house Cafe | C17: 1035 | D17: 4.7 | E17: 15/1 Lê Hồng Phong | F17: Hai Chau, Da Nang | G17: Quán sinh tố | H17: https://www.google.com/maps/search/?api=1&query=NAM%20house%20Cafe&query_place_id=ChIJTahQxcwZQjERrNKa5emQFC4 | I17: 1945
A18: Nhóm 7 | B18: Bamboo 2 Bar | C18: 1035 | D18: 4.2 | E18: 216 Bạch Đằng | F18: Hai Chau, Da Nang | G18: Quán bar | H18: https://www.google.com/maps/search/?api=1&query=Bamboo%202%20Bar&query_place_id=ChIJXdDUwzIYQjERxDBcA0prFDo | I18: 1931
A19: Nhóm 7 | B19: Olivia's Prime Steakhouse | C19: 1035 | D19: 4.6 | E19: Indochina Mall, 74 Bach Dang, Lot G1-G4, The Ground Floor | F19: Hai Chau, Da Nang | G19: Quán bar | H19: https://www.google.com/maps/search/?api=1&query=Olivia's%20Prime%20Steakhouse&query_place_id=ChIJYxCN7iwYQjERLuz4t50uWQo | I19: 1876
A20: Nhóm 7 | B20: Ky Vat - Vietnamese Restaurant | C20: 714 | D20: 4.9 | E20: 56a Lê Hồng Phong | F20: Hải Châu, Đà Nẵng | G20: restaurant | H20: https://www.google.com/maps/search/?api=1&query=Ky%20Vat%20-%20Vietnamese%20Restaurant&query_place_id=ChIJqTxk8U0ZQjERwQn9lasjeu4 | I20: 714
A21: Nhóm 7 | B21: Đồng Tiến Bakery - Lê Đình Dương | C21: 41 | D21: 4.6 | E21: 106 Lê Đình Dương | F21: Hai Chau, Da Nang | G21: Bánh mỳ | H21: https://www.google.com/maps/search/?api=1&query=%C4%90%E1%BB%93ng%20Ti%E1%BA%BFn%20Bakery%20-%20L%C3%AA%20%C4%90%C3%ACnh%20D%C6%B0%C6%A1ng&query_place_id=ChIJZeTXMw8ZQjERlEwh2alOLPU | I21: 41
B22: Tổng nhóm | C22: =SUM(C13:C21) -> 8000
A24: Nhóm 10 | B24: Boulevard Gelato, Pastry & Coffee | C24: 1035 | D24: 4.4 | E24: 77 Trần Quốc Toản | F24: Hai Chau, Da Nang | G24: Quán kem | H24: https://www.google.com/maps/search/?api=1&query=Boulevard%20Gelato%2C%20Pastry%20%26%20Coffee&query_place_id=ChIJq8DocTMYQjERrIcBZUiEnSM | I24: 1582
A25: Nhóm 10 | B25: Gang Yu Hot Pot | C25: 1035 | D25: 4.8 | E25: 87 Yên Bái | F25: Hai Chau, Da Nang | G25: Quán nhậu | H25: https://www.google.com/maps/search/?api=1&query=Gang%20Yu%20Hot%20Pot&query_place_id=ChIJ-VaWslgZQjERwaL3uKR9fB4 | I25: 1576
A26: Nhóm 10 | B26: WONDERLUST - Coffee & Souvenir | C26: 1035 | D26: 4.5 | E26: 96 Trần Phú | F26: Hai Chau, Da Nang | G26: Quán bar | H26: https://www.google.com/maps/search/?api=1&query=WONDERLUST%20-%20Coffee%20%26%20Souvenir&query_place_id=ChIJQRIRJDIYQjER4JvYKu_Qnak | I26: 1567
A27: Nhóm 10 | B27: Út Tịch café | C27: 1035 | D27: 4.5 | E27: 73 Nguyễn Thái Học | F27: Hai Chau, Da Nang | G27: Quán bar | H27: https://www.google.com/maps/search/?api=1&query=%C3%9At%20T%E1%BB%8Bch%20caf%C3%A9&query_place_id=ChIJnedjAtoZQjERMCfdOOcOaaA | I27: 1562
A28: Nhóm 10 | B28: OQ Club | C28: 1035 | D28: 4.4 | E28: 18-20 Bạch Đằng | F28: Hai Chau, Da Nang | G28: Beer club | H28: https://www.google.com/maps/search/?api=1&query=OQ%20Club&query_place_id=ChIJAQ5_dEYZQjERFybDTm99Gzk | I28: 1555
A29: Nhóm 10 | B29: Truc Lam Vien Cafe & Restaurant | C29: 1035 | D29: 4.5 | E29: 08 Trần Quý Cáp | F29: Hai Chau, Da Nang | G29: Quán nhậu | H29: https://www.google.com/maps/search/?api=1&query=Truc%20Lam%20Vien%20Cafe%20%26%20Restaurant&query_place_id=ChIJvZBNfjEYQjERa3oF_Rc2lC8 | I29: 1549
A30: Nhóm 10 | B30: Phuc Long Coffee & Tea | C30: 1035 | D30: 4 | E30: 59-61 Nguyễn Văn Linh | F30: Hai Chau, Da Nang | G30: Quán chè | H30: https://www.google.com/maps/search/?api=1&query=Phuc%20Long%20Coffee%20%26%20Tea&query_place_id=ChIJU25zBZsZQjERw6uhD10SQgo | I30: 1544
A31: Nhóm 10 | B31: A-kopi Coffee | C31: 711 | D31: 4.7 | E31: 83 Trần Phú | F31: Hai Chau, Da Nang | G31: Quán bar | H31: https://www.google.com/maps/search/?api=1&query=A-kopi%20Coffee&query_place_id=ChIJy9o9jVAZQjERbIUGn68PeTo | I31: 711
A32: Nhóm 10 | B32: quán bò kho | C32: 44 | D32: 3.9 | E32: 144 Huỳnh Thúc Kháng | F32: Hai Chau, Da Nang | G32: Bánh mỳ | H32: https://www.google.com/maps/search/?api=1&query=qu%C3%A1n%20b%C3%B2%20kho&query_place_id=ChIJBekwwKkZQjERVVWVzAwADzs | I32: 44
B33: Tổng nhóm | C33: =SUM(C24:C32) -> 8000
A35: Nhóm 15 | B35: Nhà hàng Bếp | C35: 1035 | D35: 4.6 | E35: 17 Nguyễn Thái Học | F35: Hải Châu, Đà Nẵng | G35: Nhà hàng hải sản | H35: https://www.google.com/maps/search/?api=1&query=Nh%C3%A0%20h%C3%A0ng%20B%E1%BA%BFp&query_place_id=ChIJBW5bmIMZQjER0zjjQiukdE8 | I35: 1306
A36: Nhóm 15 | B36: Red Sky Steakhouse | C36: 1035 | D36: 4.7 | E36: 248 Trần Phú | F36: Hai Chau, Da Nang | G36: Quán bar | H36: https://www.google.com/maps/search/?api=1&query=Red%20Sky%20Steakhouse&query_place_id=ChIJf_EWJM0ZQjERbBl1k_zLzyM | I36: 1305
A37: Nhóm 15 | B37: Gong Cha Nguyễn Văn Linh | C37: 1035 | D37: 4 | E37: 1 Nguyễn Văn Linh | F37: Hai Chau, Da Nang | G37: Club | H37: https://www.google.com/maps/search/?api=1&query=Gong%20Cha%20Nguy%E1%BB%85n%20V%C4%83n%20Linh&query_place_id=ChIJh1LBe_IZQjER8mNnOVlabEc | I37: 1300
A38: Nhóm 15 | B38: TOXIC City | C38: 1035 | D38: 4.4 | E38: 62-63 Trần Văn Trứ | F38: Hoa Cuong, Da Nang | G38: Quán bar | H38: https://www.google.com/maps/search/?api=1&query=TOXIC%20City&query_place_id=ChIJ1bGBeBgZQjERS6a41QRIKuk | I38: 1285
A39: Nhóm 15 | B39: Túc Tắc Tea Đà Nẵng - Hải Phòng | C39: 1035 | D39: 4.6 | E39: 07 Hải Phòng | F39: Hai Chau, Da Nang | G39: Quán trà sữa | H39: https://www.google.com/maps/search/?api=1&query=T%C3%BAc%20T%E1%BA%AFc%20Tea%20%C4%90%C3%A0%20N%E1%BA%B5ng%20-%20H%E1%BA%A3i%20Ph%C3%B2ng&query_place_id=ChIJvx1_ReAZQjERqOgXKHC3UPE | I39: 1281
A40: Nhóm 15 | B40: S'Story Coffee & Kitchen | C40: 1035 | D40: 4.9 | E40: Huỳnh Thúc Kháng/119 Bình Hiên | F40: Hai Chau, Da Nang | G40: Rooftop bar | H40: https://www.google.com/maps/search/?api=1&query=S'Story%20Coffee%20%26%20Kitchen&query_place_id=ChIJlaQFd8IZQjERCnuZnirYstQ | I40: 1269
A41: Nhóm 15 | B41: Cơm Nhà Nội Restaurant | C41: 1035 | D41: 4.8 | E41: 50 Yên Bái | F41: Hải Châu, Đà Nẵng | G41: restaurant | H41: https://www.google.com/maps/search/?api=1&query=C%C6%A1m%20Nh%C3%A0%20N%E1%BB%99i%20Restaurant&query_place_id=ChIJ619_NQAZQjER03LN6732rkg | I41: 1265
A42: Nhóm 15 | B42: Banh Xeo CUOI Restaurant (Branch 2) - Authentic Vietnamese Cuisines | C42: 692 | D42: 4.6 | E42: 197 Trần Phú | F42: Hải Châu, Đà Nẵng | G42: Quán ăn tối | H42: https://www.google.com/maps/search/?api=1&query=Banh%20Xeo%20CUOI%20Restaurant%20(Branch%202)%20-%20Authentic%20Vietnamese%20Cuisines&query_place_id=ChIJLXKy4W8XQjEREdT0u-m_bV4 | I42: 692
A43: Nhóm 15 | B43: Metta Coffee & Ice Cream | C43: 63 | D43: 4.9 | E43: 45 Cô Giang | F43: Hai Chau, Da Nang | G43: Quán kem | H43: https://www.google.com/maps/search/?api=1&query=Metta%20Coffee%20%26%20Ice%20Cream&query_place_id=ChIJj2zJfAAZQjERSQhoH_p2PxI | I43: 63
B44: Tổng nhóm | C44: =SUM(C35:C43) -> 8000
A46: Nhóm 18 | B46: Lẩu Hương Cảng | C46: 1035 | D46: 4.3 | E46: 95 Lê Lợi | F46: Hải Châu, Đà Nẵng | G46: Nhà hàng buffet | H46: https://www.google.com/maps/search/?api=1&query=L%E1%BA%A9u%20H%C6%B0%C6%A1ng%20C%E1%BA%A3ng&query_place_id=ChIJca_HnG4ZQjERdxn8nFkto38 | I46: 1090
A47: Nhóm 18 | B47: Kichi Kichi Nguyen Van Linh | C47: 1035 | D47: 4.4 | E47: 9 Nguyễn Văn Linh | F47: Hai Chau, Da Nang | G47: Quán nhậu | H47: https://www.google.com/maps/search/?api=1&query=Kichi%20Kichi%20Nguyen%20Van%20Linh&query_place_id=ChIJO317WcwZQjERtCy4WGEXcQ8 | I47: 1087
A48: Nhóm 18 | B48: Bếp Hên restaurant | C48: 1035 | D48: 4.4 | E48: 47 Lê Hồng Phong | F48: Hải Châu, Đà Nẵng | G48: Nhà hàng Nhật Bản | H48: https://www.google.com/maps/search/?api=1&query=B%E1%BA%BFp%20H%C3%AAn%20restaurant&query_place_id=ChIJxWYwXbgZQjER6Lk0IHjtq0k | I48: 1083
A49: Nhóm 18 | B49: GoGi House Nguyễn Văn Linh | C49: 1035 | D49: 4.5 | E49: 09, 9 Nguyễn Văn Linh | F49: Hải Châu, Đà Nẵng | G49: restaurant | H49: https://www.google.com/maps/search/?api=1&query=GoGi%20House%20Nguy%E1%BB%85n%20V%C4%83n%20Linh&query_place_id=ChIJqSaOi_IZQjERvek3at35ZLw | I49: 1076
A50: Nhóm 18 | B50: Reply 1988 Cafe | C50: 1035 | D50: 4.6 | E50: 45 Lê Hồng Phong | F50: Hai Chau, Da Nang | G50: Club | H50: https://www.google.com/maps/search/?api=1&query=Reply%201988%20Cafe&query_place_id=ChIJxX--D-oZQjERQ4LzQRoeVXk | I50: 1065
A51: Nhóm 18 | B51: Nhà hàng Hàn Quốc Seoul Express | C51: 1035 | D51: 4.8 | E51: 88 - 90 Nguyễn Văn Linh | F51: Hai Chau, Da Nang | G51: Bánh mỳ | H51: https://www.google.com/maps/search/?api=1&query=Nh%C3%A0%20h%C3%A0ng%20H%C3%A0n%20Qu%E1%BB%91c%20Seoul%20Express&query_place_id=ChIJ5aFAGQAZQjERBbTw-LJmbrs | I51: 1064
A52: Nhóm 18 | B52: CAFE GREEN (카페그린) 다낭, 망고빙수 | C52: 1035 | D52: 4.5 | E52: 54 Nguyễn Thái Học | F52: Hai Chau, Da Nang | G52: Cafe | H52: https://www.google.com/maps/search/?api=1&query=CAFE%20GREEN%20(%EC%B9%B4%ED%8E%98%EA%B7%B8%EB%A6%B0)%20%EB%8B%A4%EB%82%AD%2C%20%EB%A7%9D%EA%B3%A0%EB%B9%99%EC%88%98&query_place_id=ChIJY4Jt38AZQjERdO3AnO-MyAg | I52: 1044
A53: Nhóm 18 | B53: Hook No Nê - Thaifood&ThaiTea | C53: 680 | D53: 4.6 | E53: 39 Hoàng Văn Thụ | F53: Hải Châu, Đà Nẵng | G53: Nhà hàng gia đình | H53: https://www.google.com/maps/search/?api=1&query=Hook%20No%20N%C3%AA%20-%20Thaifood%26ThaiTea&query_place_id=ChIJY4B8PwAZQjERMP2sxXTeD9c | I53: 680
A54: Nhóm 18 | B54: s.core cafe | coffee shop | C54: 75 | D54: 4.9 | E54: 17 Thanh Sơn 2 | F54: Hai Chau, Da Nang | G54: Coffee | H54: https://www.google.com/maps/search/?api=1&query=s.core%20cafe%20%7C%20coffee%20shop&query_place_id=ChIJ9S-KT5AZQjERvPZ1OMZp3RU | I54: 75
B55: Tổng nhóm | C55: =SUM(C46:C54) -> 8000
A57: Nhóm 23 | B57: Ngoan Studio | C57: 773 | D57: 4.9 | E57: 149 Ông Ích Khiêm | F57: Hải Châu, Đà Nẵng | G57: Quán ăn sáng | H57: https://www.google.com/maps/search/?api=1&query=Ngoan%20Studio&query_place_id=ChIJrX7Z3UkYQjERsvJNj8kHzbg | I57: 773
A58: Nhóm 23 | B58: Bếp của ngoại CN 3 | C58: 765 | D58: 4.3 | E58: 50 Đ. 2 Tháng 9 | F58: Hải Châu, Đà Nẵng | G58: restaurant | H58: https://www.google.com/maps/search/?api=1&query=B%E1%BA%BFp%20c%E1%BB%A7a%20ngo%E1%BA%A1i%20CN%203&query_place_id=ChIJJYyeU3MZQjERMSrFxuFXcxY | I58: 765
A59: Nhóm 23 | B59: Vị brewhouse -xưởng Bia thủ công Đà Nẵng - Craft beer & Restaurant (베트남식당) - | C59: 674 | D59: 4.7 | E59: 37 Quang Trung | F59: Hai Chau, Da Nang | G59: Craft beer | H59: https://www.google.com/maps/search/?api=1&query=V%E1%BB%8B%20brewhouse%20-x%C6%B0%E1%BB%9Fng%20Bia%20th%E1%BB%A7%20c%C3%B4ng%20%C4%90%C3%A0%20N%E1%BA%B5ng%20-%20Craft%20beer%20%26%20Restaurant%20(%EB%B2%A0%ED%8A%B8%EB%82%A8%EC%8B%9D%EB%8B%B9)%20-&query_place_id=ChIJyTsD6rEZQjER1mznk4e95wc | I59: 674
A60: Nhóm 23 | B60: Gyu Sachi - Nhà hàng nướng Nhật Ngưu Hạnh | C60: 674 | D60: 4.7 | E60: 54-56 Quang Trung | F60: Hải Châu, Đà Nẵng | G60: Nhà hàng buffet | H60: https://www.google.com/maps/search/?api=1&query=Gyu%20Sachi%20-%20Nh%C3%A0%20h%C3%A0ng%20n%C6%B0%E1%BB%9Bng%20Nh%E1%BA%ADt%20Ng%C6%B0u%20H%E1%BA%A1nh&query_place_id=ChIJJSd-naoZQjERheTI-IEkRrc | I60: 674
A61: Nhóm 23 | B61: The Thai Cuisine | C61: 672 | D61: 4 | E61: Lô A26 Đ. 2 Tháng 9 | F61: Hòa Cường, Đà Nẵng | G61: restaurant | H61: https://www.google.com/maps/search/?api=1&query=The%20Thai%20Cuisine&query_place_id=ChIJ6bSjkiQZQjER7cp5bhBfHL0 | I61: 672
A62: Nhóm 23 | B62: Zen Coffee | C62: 671 | D62: 4.8 | E62: 134 Yên Bái | F62: Hai Chau, Da Nang | G62: Coffee | H62: https://www.google.com/maps/search/?api=1&query=Zen%20Coffee&query_place_id=ChIJJRuSOY0ZQjER6KVLEJqDBms | I62: 671
A63: Nhóm 23 | B63: Don Chicken 돈 치킨 | C63: 670 | D63: 4.4 | E63: 209 Nguyễn Văn Linh | F63: Thanh Khê, Đà Nẵng | G63: restaurant | H63: https://www.google.com/maps/search/?api=1&query=Don%20Chicken%20%EB%8F%88%20%EC%B9%98%ED%82%A8&query_place_id=ChIJN3qkhVUZQjERVaJrHIV4kYw | I63: 670
A64: Nhóm 23 | B64: Bánh Xèo Bà Tuyết | C64: 664 | D64: 4.7 | E64: 25/16 Trần Quốc Toản | F64: Hải Châu, Đà Nẵng | G64: Quán ăn tối | H64: https://www.google.com/maps/search/?api=1&query=B%C3%A1nh%20X%C3%A8o%20B%C3%A0%20Tuy%E1%BA%BFt&query_place_id=ChIJDwy1epoZQjER4CfJOHsL0kk | I64: 664
A65: Nhóm 23 | B65: Brilliant Top Bar | C65: 663 | D65: 4.7 | E65: 162 Bạch Đằng | F65: Hai Chau, Da Nang | G65: Rooftop bar | H65: https://www.google.com/maps/search/?api=1&query=Brilliant%20Top%20Bar&query_place_id=ChIJH7cKY9YZQjERcKzAn0dYp7g | I65: 663
A66: Nhóm 23 | B66: Mangetsu Shochu Bar - Đà Nẵng | C66: 659 | D66: 4.8 | E66: 12 Nguyễn Văn Linh | F66: Hai Chau, Da Nang | G66: Bánh mỳ | H66: https://www.google.com/maps/search/?api=1&query=Mangetsu%20Shochu%20Bar%20-%20%C4%90%C3%A0%20N%E1%BA%B5ng&query_place_id=ChIJiWT7gFgZQjER7yWmdVYxcag | I66: 659
A67: Nhóm 23 | B67: DOM Bistro | C67: 646 | D67: 4.8 | E67: 3 Phan Bội Châu | F67: Hai Chau, Da Nang | G67: Quán nhậu | H67: https://www.google.com/maps/search/?api=1&query=DOM%20Bistro&query_place_id=ChIJ7RxG8zsYQjERPiPIN76cPWw | I67: 646
A68: Nhóm 23 | B68: Bánh Mì BÀ RY I Madam Ry | C68: 466 | D68: 4.3 | E68: 36 Đ. Đào Tấn | F68: Hải Châu, Đà Nẵng | G68: restaurant | H68: https://www.google.com/maps/search/?api=1&query=B%C3%A1nh%20M%C3%AC%20B%C3%80%20RY%20I%20Madam%20Ry&query_place_id=ChIJy3cRHMEZQjERnvX6k6z71nQ | I68: 466
A69: Nhóm 23 | B69: Dine Danang | C69: 3 | D69: 5 | E69: 46 Bàu Hạc 5 | F69: Thanh Khe, Da Nang | G69: Quán bar | H69: https://www.google.com/maps/search/?api=1&query=Dine%20Danang&query_place_id=ChIJ06eLm-gZQjER7hemkFjfyZ8 | I69: 3
B70: Tổng nhóm | C70: =SUM(C57:C69) -> 8000
A72: Nhóm 26 | B72: KYOTO Yakiniku - Buffet Nướng Nhật Bản | C72: 571 | D72: 4.7 | E72: 04 Đ. Chi Lăng | F72: Hải Châu, Đà Nẵng | G72: Nhà hàng buffet | H72: https://www.google.com/maps/search/?api=1&query=KYOTO%20Yakiniku%20-%20Buffet%20N%C6%B0%E1%BB%9Bng%20Nh%E1%BA%ADt%20B%E1%BA%A3n&query_place_id=ChIJk3ydXgAZQjER5UWodI2mumI | I72: 571
A73: Nhóm 26 | B73: Nhà hàng Nhỏ Nhậu | C73: 570 | D73: 4.8 | E73: 142 Yên Bái | F73: Hai Chau, Da Nang | G73: Quán nhậu | H73: https://www.google.com/maps/search/?api=1&query=Nh%C3%A0%20h%C3%A0ng%20Nh%E1%BB%8F%20Nh%E1%BA%ADu&query_place_id=ChIJ_RylLwAZQjERnNGNlUJiQ8Y | I73: 570
A74: Nhóm 26 | B74: MUDAN HOTPOT RESTAURANT | C74: 568 | D74: 4.6 | E74: 166 Phan Châu Trinh | F74: Hải Châu, Đà Nẵng | G74: restaurant | H74: https://www.google.com/maps/search/?api=1&query=MUDAN%20HOTPOT%20RESTAURANT&query_place_id=ChIJ6xNIhTkZQjERqrVyyz44t7g | I74: 568
A75: Nhóm 26 | B75: Nhà hàng 삼덕면옥 | C75: 563 | D75: 4.6 | E75: 160 Trần Phú | F75: Hải Châu, Đà Nẵng | G75: Nhà hàng Hàn Quốc | H75: https://www.google.com/maps/search/?api=1&query=Nh%C3%A0%20h%C3%A0ng%20%EC%82%BC%EB%8D%95%EB%A9%B4%EC%98%A5&query_place_id=ChIJDRL5a4QZQjERHQqrFeCQkQ8 | I75: 563
A76: Nhóm 26 | B76: TÔ QUÁN- BÚN CHẢ HÀ NỘI- PHỞ GÀ- BÚN THANG- KEM TRÀNG TIỀN | C76: 555 | D76: 4.6 | E76: 80 Quang Trung | F76: Hải Châu, Đà Nẵng | G76: Quán bún | H76: https://www.google.com/maps/search/?api=1&query=T%C3%94%20QU%C3%81N-%20B%C3%9AN%20CH%E1%BA%A2%20H%C3%80%20N%E1%BB%98I-%20PH%E1%BB%9E%20G%C3%80-%20B%C3%9AN%20THANG-%20KEM%20TR%C3%80NG%20TI%E1%BB%80N&query_place_id=ChIJHeTGQzcYQjERBuyAhnIIrC4 | I76: 555
A77: Nhóm 26 | B77: Nhà Hàng Bếp Xưa | C77: 551 | D77: 4.4 | E77: 27 Nguyễn Chí Thanh | F77: Hải Châu, Đà Nẵng | G77: Nhà hàng | H77: https://www.google.com/maps/search/?api=1&query=Nh%C3%A0%20H%C3%A0ng%20B%E1%BA%BFp%20X%C6%B0a&query_place_id=ChIJjXCzLdQZQjERUh-BjkLvlg0 | I77: 551
A78: Nhóm 26 | B78: HiRu Sushi | C78: 544 | D78: 4.8 | E78: 35 Lê Hồng Phong | F78: Hải Châu, Đà Nẵng | G78: Quán ăn tối | H78: https://www.google.com/maps/search/?api=1&query=HiRu%20Sushi&query_place_id=ChIJ-3FfDjEZQjERYXM3lVw-a-M | I78: 544
A79: Nhóm 26 | B79: Cơm nhà Kiều Thị - 68 Đường 2/9 Đà Nẵng | C79: 539 | D79: 4.4 | E79: Đ. 2 Tháng 9/70 Bình Hiên | F79: Hai Chau, Da Nang | G79: Quán bar | H79: https://www.google.com/maps/search/?api=1&query=C%C6%A1m%20nh%C3%A0%20Ki%E1%BB%81u%20Th%E1%BB%8B%20-%2068%20%C4%90%C6%B0%E1%BB%9Dng%202%2F9%20%C4%90%C3%A0%20N%E1%BA%B5ng&query_place_id=ChIJJZ1MNO8ZQjERQKsv6HqzYII | I79: 539
A80: Nhóm 26 | B80: Bia Tô Lão Đại | C80: 538 | D80: 4 | E80: 76 Đ. 3 Tháng 2 | F80: Hải Châu, Đà Nẵng | G80: Nhà hàng | H80: https://www.google.com/maps/search/?api=1&query=Bia%20T%C3%B4%20L%C3%A3o%20%C4%90%E1%BA%A1i&query_place_id=ChIJ9QtcbT4YQjERZaAwkvzKldg | I80: 538
A81: Nhóm 26 | B81: Locus Cocktail Club DaNang | C81: 533 | D81: 4.6 | E81: 6 Trần Quốc Toản | F81: Hai Chau, Da Nang | G81: Lounge bar | H81: https://www.google.com/maps/search/?api=1&query=Locus%20Cocktail%20Club%20DaNang&query_place_id=ChIJUeXha3EZQjERBTe8ZMJqrkI | I81: 533
A82: Nhóm 26 | B82: Phở Việt Béo | C82: 532 | D82: 4.2 | E82: 35 Lý Tự Trọng | F82: Hải Châu, Đà Nẵng | G82: Quán phở | H82: https://www.google.com/maps/search/?api=1&query=Ph%E1%BB%9F%20Vi%E1%BB%87t%20B%C3%A9o&query_place_id=ChIJm1niUToYQjERgzP88Z54468 | I82: 532
A83: Nhóm 26 | B83: The Powerhouse Legacy | C83: 531 | D83: 4.6 | E83: 153-157 Triệu Nữ Vương | F83: Hải Châu, Đà Nẵng | G83: Nhà hàng Việt Nam | H83: https://www.google.com/maps/search/?api=1&query=The%20Powerhouse%20Legacy&query_place_id=ChIJlZwp77MZQjERTjZTYwAd0gI | I83: 531
... A87: Nhóm 26 | B87: Hương Coffe & Yogurt & Tea | C87: 3 | D87: 5 | E87: 90 Đ. Hàn Mặc Tử | F87: Hai Chau, Da Nang | G87: Quán bar | H87: https://www.google.com/maps/search/?api=1&query=H%C6%B0%C6%A1ng%20Coffe%20%26%20Yogurt%20%26%20Tea&query_place_id=ChIJLRRU398ZQjERO-dgTqGGLv0 | I87: 3
B88: Tổng nhóm | C88: =SUM(C72:C87) -> 8000
A90: Nhóm 31 | B90: GINZA Bar & Lounge | C90: 355 | D90: 4.9 | E90: 9 Phan Bội Châu | F90: Hai Chau, Da Nang | G90: Beer club | H90: https://www.google.com/maps/search/?api=1&query=GINZA%20Bar%20%26%20Lounge&query_place_id=ChIJSYpfiOcZQjERYKZX_AdStPY | I90: 355
A91: Nhóm 31 | B91: Moss Coffee Shop 2 | C91: 353 | D91: 4.6 | E91: 02 Phan Bội Châu | F91: Hai Chau, Da Nang | G91: Coffee | H91: https://www.google.com/maps/search/?api=1&query=Moss%20Coffee%20Shop%202&query_place_id=ChIJ2_OVwmIZQjERrNNkMMg-gk4 | I91: 353
A92: Nhóm 31 | B92: Nang Ngot Patisserie | C92: 350 | D92: 4.8 | E92: 20 Phan Bội Châu | F92: Hai Chau, Da Nang | G92: Cửa hàng đồ ngọt | H92: https://www.google.com/maps/search/?api=1&query=Nang%20Ngot%20Patisserie&query_place_id=ChIJqWzGevYZQjER3-n1VQ-rVmQ | I92: 350
A93: Nhóm 31 | B93: mlem pudding | C93: 349 | D93: 4.7 | E93: 169 /3Đường Trần Phú | F93: Hai Chau, Da Nang | G93: Quán trà sữa | H93: https://www.google.com/maps/search/?api=1&query=mlem%20pudding&query_place_id=ChIJXa6BdxAZQjER-8GMkCSyShA | I93: 349
A94: Nhóm 31 | B94: LIBRE Bar DaNang | C94: 348 | D94: 4.8 | E94: 125a Nguyễn Chí Thanh | F94: Hai Chau, Da Nang | G94: Cocktail bar | H94: https://www.google.com/maps/search/?api=1&query=LIBRE%20Bar%20DaNang&query_place_id=ChIJvcXagjAYQjERCEguUGaxfEc | I94: 348
A95: Nhóm 31 | B95: Bún Bò Huế - Lê Gia Khang | C95: 348 | D95: 4.3 | E95: 372 Đống Đa | F95: Hai Chau, Da Nang | G95: Quán bánh mì | H95: https://www.google.com/maps/search/?api=1&query=B%C3%BAn%20B%C3%B2%20Hu%E1%BA%BF%20-%20L%C3%AA%20Gia%20Khang&query_place_id=ChIJox9FwvgZQjERARNTBI9eHMQ | I95: 348
A96: Nhóm 31 | B96: Cafe Mọt | C96: 348 | D96: 4.1 | E96: 147 Đống Đa | F96: Hai Chau, Da Nang | G96: Cafe | H96: https://www.google.com/maps/search/?api=1&query=Cafe%20M%E1%BB%8Dt&query_place_id=ChIJJe7cO-oZQjERiCl6uy09kII | I96: 348
A97: Nhóm 31 | B97: KITE COFFEE & SOUVENIRS | C97: 346 | D97: 4.7 | E97: 35 Thái Phiên Phường Phước Ninh Quận Hải Châu (mặt 77, Yên Bái | F97: Da Nang | G97: Quán cà phê | H97: https://www.google.com/maps/search/?api=1&query=KITE%20COFFEE%20%26%20SOUVENIRS&query_place_id=ChIJrcgyp-wZQjERNqpo6xe5Ogw | I97: 346
A98: Nhóm 31 | B98: Caro Cafe | C98: 340 | D98: 4.9 | E98: 90/1a, Trần Phú | F98: Hai Chau, Da Nang | G98: Cafe | H98: https://www.google.com/maps/search/?api=1&query=Caro%20Cafe&query_place_id=ChIJJ-Fs7lgZQjERlV88Mt1FtCA | I98: 340
A99: Nhóm 31 | B99: [91cc] 91 Concept Coffee | C99: 339 | D99: 4.8 | E99: 91 Trần Quốc Toản | F99: Hai Chau, Da Nang | G99: Coffee | H99: https://www.google.com/maps/search/?api=1&query=%5B91cc%5D%2091%20Concept%20Coffee&query_place_id=ChIJXeXlix8ZQjERx9QsmNqx6_U | I99: 339
A100: Nhóm 31 | B100: Incheon Coffee Đà Nẵng | C100: 338 | D100: 4.1 | E100: 35 Lý Thường Kiệt | F100: Hải Châu, Đà Nẵng | G100: Quán ăn trưa | H100: https://www.google.com/maps/search/?api=1&query=Incheon%20Coffee%20%C4%90%C3%A0%20N%E1%BA%B5ng&query_place_id=ChIJO_pjetcZQjERCIcUKmTka2o | I100: 338
A101: Nhóm 31 | B101: Xém. Cà Phê (K1/25 Đỗ quang) | C101: 338 | D101: 4.3 | E101: 25 Đỗ Quang | F101: Thanh Khe, Da Nang | G101: Quán sinh tố | H101: https://www.google.com/maps/search/?api=1&query=X%C3%A9m.%20C%C3%A0%20Ph%C3%AA%20(K1%2F25%20%C4%90%E1%BB%97%20quang)&query_place_id=ChIJL-fQUUcZQjERK85coinuqEk | I101: 338
... A113: Nhóm 31 | B113: Linger | C113: 315 | D113: 4.9 | E113: 58 Phạm Ngọc Thạch | F113: Hai Chau, Da Nang | G113: Wine bar | H113: https://www.google.com/maps/search/?api=1&query=Linger&query_place_id=ChIJATrb_PwZQjERO4AMR8kF2t0 | I113: 315
B114: Tổng nhóm | C114: =SUM(C90:C113) -> 8000
A116: Nhóm 34 | B116: LaBoong Đà Nẵng 332 Hoàng Diệu - Trà Ô Long Làng LaBoong | C116: 233 | D116: 4.9 | E116: 332 Hoàng Diệu | F116: Hai Chau, Da Nang | G116: Trà sữa | H116: https://www.google.com/maps/search/?api=1&query=LaBoong%20%C4%90%C3%A0%20N%E1%BA%B5ng%20332%20Ho%C3%A0ng%20Di%E1%BB%87u%20-%20Tr%C3%A0%20%C3%94%20Long%20L%C3%A0ng%20LaBoong&query_place_id=ChIJ_SfjBwwZQjERgEqvKj-1GL4 | I116: 233
A117: Nhóm 34 | B117: Cơm lu Như Ý | C117: 233 | D117: 4.8 | E117: 16 Triệu Nữ Vương | F117: Hải Châu, Đà Nẵng | G117: Quán ăn trưa | H117: https://www.google.com/maps/search/?api=1&query=C%C6%A1m%20lu%20Nh%C6%B0%20%C3%9D&query_place_id=ChIJx0RXLgAZQjER1ILFQyQZ_t8 | I117: 233
A118: Nhóm 34 | B118: TRÀ Coffee & Tea House 24/7 | C118: 233 | D118: 4.4 | E118: 66 Bạch Đằng | F118: Hai Chau, Da Nang | G118: Quán trà sữa | H118: https://www.google.com/maps/search/?api=1&query=TR%C3%80%20Coffee%20%26%20Tea%20House%2024%2F7&query_place_id=ChIJX6GHXQAZQjERSd-Au3-8I4o | I118: 233
A119: Nhóm 34 | B119: Bánh Huế Trần Thị | C119: 232 | D119: 4.4 | E119: 23 Nguyễn Hữu Cảnh | F119: Hải Châu, Đà Nẵng | G119: Quán ăn | H119: https://www.google.com/maps/search/?api=1&query=B%C3%A1nh%20Hu%E1%BA%BF%20Tr%E1%BA%A7n%20Th%E1%BB%8B&query_place_id=ChIJfZq29RUYQjERFSWBuWBLWEM | I119: 232
A120: Nhóm 34 | B120: Hương Chè Thái - Chi Lăng | C120: 232 | D120: 4.1 | E120: 45 Pasteur | F120: Hai Chau, Da Nang | G120: Quán bar | H120: https://www.google.com/maps/search/?api=1&query=H%C6%B0%C6%A1ng%20Ch%C3%A8%20Th%C3%A1i%20-%20Chi%20L%C4%83ng&query_place_id=ChIJSzMcT-sZQjERr7Wb7NFlE6o | I120: 232
A121: Nhóm 34 | B121: Nhà hàng Đông Dương | C121: 232 | D121: 4.2 | E121: 18 Trần Phú | F121: Hai Chau, Da Nang | G121: Quán nhậu | H121: https://www.google.com/maps/search/?api=1&query=Nh%C3%A0%20h%C3%A0ng%20%C4%90%C3%B4ng%20D%C6%B0%C6%A1ng&query_place_id=ChIJz8rE_MwZQjERXxeJG-d97IY | I121: 232
A122: Nhóm 34 | B122: Bánh Canh Cá Bã Trầu - Mực Câu ( Nhi ) | C122: 231 | D122: 4.9 | E122: 22 Hoàng Văn Thụ | F122: Hải Châu, Đà Nẵng | G122: Quán ăn sáng | H122: https://www.google.com/maps/search/?api=1&query=B%C3%A1nh%20Canh%20C%C3%A1%20B%C3%A3%20Tr%E1%BA%A7u%20-%20M%E1%BB%B1c%20C%C3%A2u%20(%20Nhi%20)&query_place_id=ChIJxfXpQgAZQjER7pfR5c4MWB8 | I122: 231
...

Sheet Nguyên
A1: Nhóm | B1: title | C1: reviewsCount (max 1035) | D1: totalScore | E1: street | F1: state | G1: searchString | H1: url | I1: reviewsCount gốc
A2: Nhóm 3 | B2: Bánh mì Happy Bread Mì AA | C2: 1035 | D2: 4.4 | E2: 10 Hùng Vương | F2: Hai Chau, Da Nang | G2: Bánh mỳ | H2: https://www.google.com/maps/search/?api=1&query=B%C3%A1nh%20m%C3%AC%20Happy%20Bread%20M%C3%AC%20AA&query_place_id=ChIJ89mYFzIYQjERMUUvbWbrhGY | I2: 4681
A3: Nhóm 3 | B3: On The Radio | C3: 1035 | D3: 4.7 | E3: 76 Thái Phiên | F3: Hải Châu, Đà Nẵng | G3: Quán ăn tối | H3: https://www.google.com/maps/search/?api=1&query=On%20The%20Radio&query_place_id=ChIJkZi7gkcYQjERPd87DaNuhW0 | I3: 4669
A4: Nhóm 3 | B4: LoCo Restaurant - Danang Seafood Restaurant - 다낭 레스토랑 | C4: 1035 | D4: 4.8 | E4: 1C Lê Duẩn | F4: Hai Chau, Da Nang | G4: Quán nhậu | H4: https://www.google.com/maps/search/?api=1&query=LoCo%20Restaurant%20-%20Danang%20Seafood%20Restaurant%20-%20%EB%8B%A4%EB%82%AD%20%EB%A0%88%EC%8A%A4%ED%86%A0%EB%9E%91&query_place_id=ChIJH72bVncZQjERoTgax0OjZKY | I4: 4450
A5: Nhóm 3 | B5: Dookki Indochina Riveside Đà Nẵng | C5: 1035 | D5: 4.8 | E5: Indochina Riverside Towers, Tòa nhà, Trần Phú | F5: Hải Châu, Đà Nẵng | G5: Nhà hàng buffet | H5: https://www.google.com/maps/search/?api=1&query=Dookki%20Indochina%20Riveside%20%C4%90%C3%A0%20N%E1%BA%B5ng&query_place_id=ChIJd8rQNcQZQjERGI7YqR0s9Rk | I5: 3980
A6: Nhóm 3 | B6: Ramen Yushoken | C6: 1035 | D6: 4.9 | E6: 21 Hoàng Văn Thụ | F6: Hai Chau, Da Nang | G6: Quán bar | H6: https://www.google.com/maps/search/?api=1&query=Ramen%20Yushoken&query_place_id=ChIJxyPtlkUZQjERViQHYRBx6WA | I6: 3895
A7: Nhóm 3 | B7: The 1920's Lounge | C7: 1035 | D7: 4.8 | E7: 53 Trần Quốc Toản | F7: Hai Chau, Da Nang | G7: Lounge bar | H7: https://www.google.com/maps/search/?api=1&query=The%201920's%20Lounge&query_place_id=ChIJp5h-DjMYQjERTMBHOnlub0o | I7: 3803
A8: Nhóm 3 | B8: Nhà hàng Thiên Kim | C8: 1035 | D8: 4.4 | E8: 166 Bạch Đằng | F8: Hải Châu, Đà Nẵng | G8: Nhà hàng Việt Nam | H8: https://www.google.com/maps/search/?api=1&query=Nh%C3%A0%20h%C3%A0ng%20Thi%C3%AAn%20Kim&query_place_id=ChIJw1z2gkdTNDERULJnMFS92vg | I8: 3710
A9: Nhóm 3 | B9: Chè Thái NaNa | C9: 736 | D9: 4.4 | E9: 44 Nguyễn Văn Linh | F9: Hai Chau, Da Nang | G9: Pub | H9: https://www.google.com/maps/search/?api=1&query=Ch%C3%A8%20Th%C3%A1i%20NaNa&query_place_id=ChIJhUsxrssZQjERKUuhxibO6o8 | I9: 736
A10: Nhóm 3 | B10: Quán Tồ | C10: 19 | D10: 4.3 | E10: 18 Thanh Sơn | F10: Hải Châu, Đà Nẵng | G10: restaurant | H10: https://www.google.com/maps/search/?api=1&query=Qu%C3%A1n%20T%E1%BB%93&query_place_id=ChIJtWhNbgAZQjERRd5Phtr3oV8 | I10: 19
B11: Tổng nhóm | C11: =SUM(C2:C10) -> 8000
A13: Nhóm 6 | B13: Bếp Lụa vietnamese restaurant ( 볩루아 베트남식당 ) | C13: 1035 | D13: 4.8 | E13: 94 Bạch Đằng | F13: Hải Châu, Đà Nẵng | G13: Nhà hàng buffet | H13: https://www.google.com/maps/search/?api=1&query=B%E1%BA%BFp%20L%E1%BB%A5a%20vietnamese%20restaurant%20(%20%EB%B3%A9%EB%A3%A8%EC%95%84%20%EB%B2%A0%ED%8A%B8%EB%82%A8%EC%8B%9D%EB%8B%B9%20)&query_place_id=ChIJWXnKvR4ZQjER0SEJsr0_pbo | I13: 2316
A14: Nhóm 6 | B14: Cardi Pizzeria | C14: 1035 | D14: 4.8 | E14: Đ. 2 Tháng 9/76 Bình Hiên | F14: Hai Chau, Da Nang | G14: Quán pizza | H14: https://www.google.com/maps/search/?api=1&query=Cardi%20Pizzeria&query_place_id=ChIJbQZAAW8ZQjERiDUN3Ym6tlo | I14: 2246
A15: Nhóm 6 | B15: Cơm gà A Hải | C15: 1035 | D15: 4 | E15: 100 Thái Phiên | F15: Hải Châu, Đà Nẵng | G15: Quán ăn tối | H15: https://www.google.com/maps/search/?api=1&query=C%C6%A1m%20g%C3%A0%20A%20H%E1%BA%A3i&query_place_id=ChIJ6SbLpjQYQjER5qEkmTLPcuY | I15: 2204
A16: Nhóm 6 | B16: Mì Quảng 1A | C16: 1035 | D16: 4 | E16: 5 Hải Phòng | F16: Hải Châu, Đà Nẵng | G16: Quán mỳ | H16: https://www.google.com/maps/search/?api=1&query=M%C3%AC%20Qu%E1%BA%A3ng%201A&query_place_id=ChIJX-Pc1zYYQjEROyhEA-ZYJ5g | I16: 2180
A17: Nhóm 6 | B17: Chè Liên Đà Nẵng | C17: 1035 | D17: 4.1 | E17: 189 Hoàng Diệu | F17: Hai Chau, Da Nang | G17: Quán chè | H17: https://www.google.com/maps/search/?api=1&query=Ch%C3%A8%20Li%C3%AAn%20%C4%90%C3%A0%20N%E1%BA%B5ng&query_place_id=ChIJNUmsQ0gZQjERny4iUkgPNNg | I17: 2139
A18: Nhóm 6 | B18: Gordon's New York Pizza Cityside | C18: 1035 | D18: 4.9 | E18: 226 Bạch Đằng | F18: Hải Châu, Đà Nẵng | G18: restaurant | H18: https://www.google.com/maps/search/?api=1&query=Gordon's%20New%20York%20Pizza%20Cityside&query_place_id=ChIJB2N6XLQZQjERllLczI16eHA | I18: 2097
A19: Nhóm 6 | B19: Bún chả cá 109 | C19: 1035 | D19: 4.2 | E19: 109 Nguyễn Chí Thanh | F19: Hải Châu, Đà Nẵng | G19: Quán ăn sáng | H19: https://www.google.com/maps/search/?api=1&query=B%C3%BAn%20ch%E1%BA%A3%20c%C3%A1%20109&query_place_id=ChIJuRo-ujAYQjER1Zn689p6UQQ | I19: 2092
A20: Nhóm 6 | B20: 77S Chocolate - Gifts & Chocolate Vietnamese Store | C20: 716 | D20: 5 | E20: 103 Trần Phú | F20: Hai Chau, Da Nang | G20: Tiệm bánh | H20: https://www.google.com/maps/search/?api=1&query=77S%20Chocolate%20-%20Gifts%20%26%20Chocolate%20Vietnamese%20Store&query_place_id=ChIJ1VIXuoAZQjERJJakBtmw1cg | I20: 716
A21: Nhóm 6 | B21: Trieu Hop Restaurant | C21: 39 | D21: 4.7 | E21: 26 Trần Bình Trọng | F21: Hai Chau, Da Nang | G21: Quán bar | H21: https://www.google.com/maps/search/?api=1&query=Trieu%20Hop%20Restaurant&query_place_id=ChIJqT_YkzQYQjERpig10AfRPBA | I21: 39
B22: Tổng nhóm | C22: =SUM(C13:C21) -> 8000
A24: Nhóm 11 | B24: Central Players | C24: 1035 | D24: 4.6 | E24: Lô 57 Trần Văn Trứ | F24: Hòa Cường, Đà Nẵng | G24: restaurant | H24: https://www.google.com/maps/search/?api=1&query=Central%20Players&query_place_id=ChIJTYOxAeIZQjERxcNnzSYYq14 | I24: 1543
A25: Nhóm 11 | B25: Nhà hàng Mr.Anh | C25: 1035 | D25: 4.8 | E25: 340 Ông Ích Khiêm | F25: Thanh Khê, Đà Nẵng | G25: Nhà hàng | H25: https://www.google.com/maps/search/?api=1&query=Nh%C3%A0%20h%C3%A0ng%20Mr.Anh&query_place_id=ChIJV_BGLtAZQjERD9LS1cvwDwg | I25: 1539
A26: Nhóm 11 | B26: NHÀ HÀNG HỒNG NGỌC | C26: 1035 | D26: 3.6 | E26: 193 Nguyễn Chí Thanh | F26: Hải Châu, Đà Nẵng | G26: Quán ăn tối | H26: https://www.google.com/maps/search/?api=1&query=NH%C3%80%20H%C3%80NG%20H%E1%BB%92NG%20NG%E1%BB%8CC&query_place_id=ChIJEfpBJDEYQjERjBNlSpkJj78 | I26: 1534
A27: Nhóm 11 | B27: Út Tịch Café | C27: 1035 | D27: 4.5 | E27: 102 Bạch Đằng | F27: Hai Chau, Da Nang | G27: Quán cà phê | H27: https://www.google.com/maps/search/?api=1&query=%C3%9At%20T%E1%BB%8Bch%20Caf%C3%A9&query_place_id=ChIJ58vWFWAZQjERW-fhjkVfrQM | I27: 1527
A28: Nhóm 11 | B28: Bloom Night Club | C28: 1035 | D28: 4.8 | E28: 100 Yên Bái | F28: Hai Chau, Da Nang | G28: Beer club | H28: https://www.google.com/maps/search/?api=1&query=Bloom%20Night%20Club&query_place_id=ChIJvV-OKAYZQjER5Q7O4dZyijw | I28: 1522
A29: Nhóm 11 | B29: BÁNH TRÁNG THỊT HEO ĐẠI LỘC - Quán ĐẠI LỘC 97 & 148 Trưng Nữ Vương. | C29: 1035 | D29: 4 | E29: 148 Trưng Nữ Vương | F29: Hải Châu, Đà Nẵng | G29: Quán ăn | H29: https://www.google.com/maps/search/?api=1&query=B%C3%81NH%20TR%C3%81NG%20TH%E1%BB%8AT%20HEO%20%C4%90%E1%BA%A0I%20L%E1%BB%98C%20-%20Qu%C3%A1n%20%C4%90%E1%BA%A0I%20L%E1%BB%98C%2097%20%26%20148%20Tr%C6%B0ng%20N%E1%BB%AF%20V%C6%B0%C6%A1ng.&query_place_id=ChIJkzXqpc4ZQjERZ58aWRvWqGo | I29: 1519
A30: Nhóm 11 | B30: KFC Nguyễn Văn Linh - Đà Nẵng | C30: 1035 | D30: 4.7 | E30: 148 Nguyễn Văn Linh | F30: Hải Châu, Đà Nẵng | G30: Nhà hàng gia đình | H30: https://www.google.com/maps/search/?api=1&query=KFC%20Nguy%E1%BB%85n%20V%C4%83n%20Linh%20-%20%C4%90%C3%A0%20N%E1%BA%B5ng&query_place_id=ChIJv0ja-0gZQjERPPSKulqbzJg | I30: 1518
A31: Nhóm 11 | B31: Bánh tráng thịt heo Quán Cốm Đại Lộc | C31: 699 | D31: 4.7 | E31: 103 Trưng Nữ Vương | F31: Hải Châu, Đà Nẵng | G31: Quán ăn | H31: https://www.google.com/maps/search/?api=1&query=B%C3%A1nh%20tr%C3%A1ng%20th%E1%BB%8Bt%20heo%20Qu%C3%A1n%20C%E1%BB%91m%20%C4%90%E1%BA%A1i%20L%E1%BB%99c&query_place_id=ChIJ2VicQwAZQjERnEOxyC0UA9Q | I31: 699
A32: Nhóm 11 | B32: Xôi Trúc | C32: 56 | D32: 4.8 | E32: 169 Lê Đình Dương | F32: Hai Chau, Da Nang | G32: Quán bar | H32: https://www.google.com/maps/search/?api=1&query=X%C3%B4i%20Tr%C3%BAc&query_place_id=ChIJwXpGWAAZQjERvIf6NVAl4DM | I32: 56
B33: Tổng nhóm | C33: =SUM(C24:C32) -> 8000
A35: Nhóm 14 | B35: DOOKKI GO ĐÀ NẴNG | C35: 1035 | D35: 4.8 | E35: 257 Hùng Vương | F35: Thanh Khe, Da Nang | G35: Quán bar | H35: https://www.google.com/maps/search/?api=1&query=DOOKKI%20GO%20%C4%90%C3%80%20N%E1%BA%B4NG&query_place_id=ChIJa_OfUQAZQjERfQcAUYgli_A | I35: 1386
A36: Nhóm 14 | B36: Alluvia Chocolate 08 Nguyễn Thái Học | C36: 1035 | D36: 5 | E36: 08 Nguyễn Thái Học | F36: Hai Chau, Da Nang | G36: Quán bar | H36: https://www.google.com/maps/search/?api=1&query=Alluvia%20Chocolate%2008%20Nguy%E1%BB%85n%20Th%C3%A1i%20H%E1%BB%8Dc&query_place_id=ChIJLT3SafYZQjERcALeaMTmHOI | I36: 1385
A37: Nhóm 14 | B37: HỦ TIẾU KỲ KỲ - HOÀNG VĂN THỤ | C37: 1035 | D37: 4.8 | E37: 20 Hoàng Văn Thụ | F37: Hải Châu, Đà Nẵng | G37: Quán ăn sáng | H37: https://www.google.com/maps/search/?api=1&query=H%E1%BB%A6%20TI%E1%BA%BEU%20K%E1%BB%B2%20K%E1%BB%B2%20-%20HO%C3%80NG%20V%C4%82N%20TH%E1%BB%A4&query_place_id=ChIJP0cRPt8ZQjERiwv4uPn9nU8 | I37: 1369
A38: Nhóm 14 | B38: Sanuki Udon-Mì Ngon Chuẩn Nhật | C38: 1035 | D38: 4.9 | E38: 135 Nguyễn Văn Linh | F38: Hải Châu, Đà Nẵng | G38: Nhà hàng Nhật Bản | H38: https://www.google.com/maps/search/?api=1&query=Sanuki%20Udon-M%C3%AC%20Ngon%20Chu%E1%BA%A9n%20Nh%E1%BA%ADt&query_place_id=ChIJV4JI6XQZQjERmVWu8gpEqTQ | I38: 1353
A39: Nhóm 14 | B39: Lẩu Bò Triều Châu WangHeNiu Đà Nẵng - 旺和牛潮汕牛肉火锅 (岘港） | C39: 1035 | D39: 4.7 | E39: 24 Pasteur | F39: Hải Châu, Đà Nẵng | G39: Quán ăn tối | H39: https://www.google.com/maps/search/?api=1&query=L%E1%BA%A9u%20B%C3%B2%20Tri%E1%BB%81u%20Ch%C3%A2u%20WangHeNiu%20%C4%90%C3%A0%20N%E1%BA%B5ng%20-%20%E6%97%BA%E5%92%8C%E7%89%9B%E6%BD%AE%E6%B1%95%E7%89%9B%E8%82%89%E7%81%AB%E9%94%85%20(%E5%B2%98%E6%B8%AF%EF%BC%89&query_place_id=ChIJpdc2oT0ZQjERQck5OlhxA7s | I39: 1341
A40: Nhóm 14 | B40: Shin Sushi | C40: 1035 | D40: 4.8 | E40: 69 Thái Phiên | F40: Hải Châu, Đà Nẵng | G40: Quán ăn tối | H40: https://www.google.com/maps/search/?api=1&query=Shin%20Sushi&query_place_id=ChIJYbH5FXIZQjERYn7Pdr11FP4 | I40: 1308
A41: Nhóm 14 | B41: 켓 바 1 Kết Bar | C41: 1035 | D41: 4.9 | E41: 04 Phan Kế Bính | F41: Hai Chau, Da Nang | G41: Lounge bar | H41: https://www.google.com/maps/search/?api=1&query=%EC%BC%93%20%EB%B0%94%201%20K%E1%BA%BFt%20Bar&query_place_id=ChIJu9GUjOgZQjERpfx8z-GIMEw | I41: 1308
A42: Nhóm 14 | B42: Beer Hub - Nhà Hàng Bia Tươi Đức | C42: 693 | D42: 4.3 | E42: 79 nguyễn văn linh,phường phước ninh, 79 Nguyễn Văn Linh | F42: Hai Chau, Da Nang | G42: Beer club | H42: https://www.google.com/maps/search/?api=1&query=Beer%20Hub%20-%20Nh%C3%A0%20H%C3%A0ng%20Bia%20T%C6%B0%C6%A1i%20%C4%90%E1%BB%A9c&query_place_id=ChIJj4MCsjIZQjERRnZtquFLfmY | I42: 693
A43: Nhóm 14 | B43: Bánh canh cá lóc TƠ | C43: 62 | D43: 4 | E43: 140 Lê Đình Dương | F43: Hải Châu, Đà Nẵng | G43: restaurant | H43: https://www.google.com/maps/search/?api=1&query=B%C3%A1nh%20canh%20c%C3%A1%20l%C3%B3c%20T%C6%A0&query_place_id=ChIJpZMpDssZQjERHX2XG82Yf3U | I43: 62
B44: Tổng nhóm | C44: =SUM(C35:C43) -> 8000
A46: Nhóm 19 | B46: Cơm tấm Bà Lang | C46: 1035 | D46: 4.4 | E46: 120 Yên Bái | F46: Hải Châu, Đà Nẵng | G46: Quán phở | H46: https://www.google.com/maps/search/?api=1&query=C%C6%A1m%20t%E1%BA%A5m%20B%C3%A0%20Lang&query_place_id=ChIJnXpgIjMYQjERZFXDhkGGiHM | I46: 1039
A47: Nhóm 19 | B47: Edo Sushi | C47: 1029 | D47: 4.4 | E47: 27 Thái Phiên | F47: Hải Châu, Đà Nẵng | G47: Quán ăn tối | H47: https://www.google.com/maps/search/?api=1&query=Edo%20Sushi&query_place_id=ChIJnygfJDMYQjERZ_bToLU1Rp8 | I47: 1029
A48: Nhóm 19 | B48: P Coffee | C48: 1005 | D48: 4.5 | E48: 53-55 Nguyễn Văn Linh | F48: Hai Chau, Da Nang | G48: Cửa hàng bánh ngọt | H48: https://www.google.com/maps/search/?api=1&query=P%20Coffee&query_place_id=ChIJxzo3j9EZQjER785qACnbIW0 | I48: 1005
A49: Nhóm 19 | B49: VIN Tea | C49: 992 | D49: 4.6 | E49: 187 Phan Châu Trinh | F49: Hai Chau, Da Nang | G49: Quán trà sữa | H49: https://www.google.com/maps/search/?api=1&query=VIN%20Tea&query_place_id=ChIJY5T3d8gZQjERh7lRe0x8ezU | I49: 992
A50: Nhóm 19 | B50: 1710 Cafe & Society | C50: 983 | D50: 4.8 | E50: 10 Trần Quý Cáp | F50: Hải Châu, Đà Nẵng | G50: restaurant | H50: https://www.google.com/maps/search/?api=1&query=1710%20Cafe%20%26%20Society&query_place_id=ChIJgzrhDjMZQjER0CL2o1oxNKo | I50: 983
A51: Nhóm 19 | B51: Cà Phê Trứng 3T - Cầu Rồng - Đà Nẵng | C51: 954 | D51: 4.5 | E51: 186 Bạch Đằng | F51: Hai Chau, Da Nang | G51: Quán trà sữa | H51: https://www.google.com/maps/search/?api=1&query=C%C3%A0%20Ph%C3%AA%20Tr%E1%BB%A9ng%203T%20-%20C%E1%BA%A7u%20R%E1%BB%93ng%20-%20%C4%90%C3%A0%20N%E1%BA%B5ng&query_place_id=ChIJPwdZFNsZQjERvlVXqS9zHNI | I51: 954
A52: Nhóm 19 | B52: Phở Thảo | C52: 953 | D52: 4.8 | E52: 08 Trần Quốc Toản | F52: Hải Châu, Đà Nẵng | G52: Quán phở | H52: https://www.google.com/maps/search/?api=1&query=Ph%E1%BB%9F%20Th%E1%BA%A3o&query_place_id=ChIJUXLENfkZQjERx7SxxRzpaBw | I52: 953
A53: Nhóm 19 | B53: Namto House Coffee & Vietnamese Cuisine | C53: 945 | D53: 4.4 | E53: 130 Nguyễn Chí Thanh | F53: Hai Chau, Da Nang | G53: Quán bar | H53: https://www.google.com/maps/search/?api=1&query=Namto%20House%20Coffee%20%26%20Vietnamese%20Cuisine&query_place_id=ChIJHaJ3RZ8ZQjER2YGM4jUgFZ4 | I53: 945
A54: Nhóm 19 | B54: Vạn Hợp Long - Sâm Yến Đông Trùng | C54: 104 | D54: 4.9 | E54: 106 Phan Châu Trinh | F54: Hai Chau, Da Nang | G54: Cửa hàng đồ ngọt | H54: https://www.google.com/maps/search/?api=1&query=V%E1%BA%A1n%20H%E1%BB%A3p%20Long%20-%20S%C3%A2m%20Y%E1%BA%BFn%20%C4%90%C3%B4ng%20Tr%C3%B9ng&query_place_id=ChIJAQC0fLMZQjERHrd-R5krjl8 | I54: 104
B55: Tổng nhóm | C55: =SUM(C46:C54) -> 8000
A57: Nhóm 22 | B57: IZAKAYA YOSHINO SHOTEN 居酒屋芳野商店ダナン | C57: 836 | D57: 4.9 | E57: 119 Hoàng Văn Thụ | F57: Hải Châu, Đà Nẵng | G57: restaurant | H57: https://www.google.com/maps/search/?api=1&query=IZAKAYA%20YOSHINO%20SHOTEN%20%E5%B1%85%E9%85%92%E5%B1%8B%E8%8A%B3%E9%87%8E%E5%95%86%E5%BA%97%E3%83%80%E3%83%8A%E3%83%B3&query_place_id=ChIJWynPWAAZQjERmOFv986R9Tk | I57: 836
A58: Nhóm 22 | B58: Tê Bar | C58: 829 | D58: 4.7 | E58: 3rd Floor, 39-41 Nguyễn Thái Học | F58: Hai Chau, Da Nang | G58: Cocktail bar | H58: https://www.google.com/maps/search/?api=1&query=T%C3%AA%20Bar&query_place_id=ChIJYZuMDnEZQjERrftd297ekRM | I58: 829
A59: Nhóm 22 | B59: Alluvia Chocolate 06 Hung Vuong | C59: 828 | D59: 5 | E59: 06 Hùng Vương | F59: Hai Chau, Da Nang | G59: Tiệm bánh | H59: https://www.google.com/maps/search/?api=1&query=Alluvia%20Chocolate%2006%20Hung%20Vuong&query_place_id=ChIJo0eUOC4ZQjER2S7NTkOvrFs | I59: 828
A60: Nhóm 22 | B60: Phở Ngọc | C60: 821 | D60: 4.9 | E60: 25 Pasteur | F60: Hai Chau, Da Nang | G60: Quán bar | H60: https://www.google.com/maps/search/?api=1&query=Ph%E1%BB%9F%20Ng%E1%BB%8Dc&query_place_id=ChIJfe5TkFwZQjERM_vJMk0Fbyo | I60: 821
A61: Nhóm 22 | B61: Phở Cổ | C61: 811 | D61: 4.7 | E61: 74 Thái Phiên | F61: Hai Chau, Da Nang | G61: Beer club | H61: https://www.google.com/maps/search/?api=1&query=Ph%E1%BB%9F%20C%E1%BB%95&query_place_id=ChIJ-8ZiS8IZQjERZxAsTrpk3RM | I61: 811
A62: Nhóm 22 | B62: Bông Food & Drink | C62: 807 | D62: 4.4 | E62: 44 Đ. 2 Tháng 9 | F62: Hai Chau, Da Nang | G62: Cửa hàng bánh ngọt | H62: https://www.google.com/maps/search/?api=1&query=B%C3%B4ng%20Food%20%26%20Drink&query_place_id=ChIJtaSFoeEZQjERCsOWikO4fKk | I62: 807
A63: Nhóm 22 | B63: Ẩm thực Trần - 11 Nguyễn Văn Linh, Đà Nẵng | C63: 795 | D63: 3.3 | E63: Nguyễn Văn Linh/11 Bình Hiên | F63: Hải Châu, Đà Nẵng | G63: Nhà hàng gia đình | H63: https://www.google.com/maps/search/?api=1&query=%E1%BA%A8m%20th%E1%BB%B1c%20Tr%E1%BA%A7n%20-%2011%20Nguy%E1%BB%85n%20V%C4%83n%20Linh%2C%20%C4%90%C3%A0%20N%E1%BA%B5ng&query_place_id=ChIJT2TVe4oZQjERXntmuHijgdE | I63: 795
A64: Nhóm 22 | B64: Brewman Coffee Concept | C64: 790 | D64: 4.6 | E64: K27a/21 Thái Phiên | F64: Hai Chau, Da Nang | G64: Quán cà phê | H64: https://www.google.com/maps/search/?api=1&query=Brewman%20Coffee%20Concept&query_place_id=ChIJkc7G1zIYQjERr0D55dn6IEc | I64: 790
A65: Nhóm 22 | B65: Mì Quảng Đà Nẵng - Mỳ Quảng Bà Mua | C65: 775 | D65: 4.1 | E65: 44 Lê Đình Dương | F65: Hải Châu, Đà Nẵng | G65: restaurant | H65: https://www.google.com/maps/search/?api=1&query=M%C3%AC%20Qu%E1%BA%A3ng%20%C4%90%C3%A0%20N%E1%BA%B5ng%20-%20M%E1%BB%B3%20Qu%E1%BA%A3ng%20B%C3%A0%20Mua&query_place_id=ChIJ8QAt0_UZQjERGMEFDl5mapA | I65: 775
A66: Nhóm 22 | B66: Hannam korean food 한남식당 | C66: 677 | D66: 4.6 | E66: 73 Nguyễn Văn Linh | F66: Hải Châu, Đà Nẵng | G66: Nhà hàng gia đình | H66: https://www.google.com/maps/search/?api=1&query=Hannam%20korean%20food%20%ED%95%9C%EB%82%A8%EC%8B%9D%EB%8B%B9&query_place_id=ChIJyfYWXloZQjERDS4b3hqyDmc | I66: 677
A67: Nhóm 22 | B67: LEILA HOUSE | C67: 31 | D67: 5 | E67: 308/14 Hoàng Diệu | F67: Hai Chau, Da Nang | G67: Quán nhậu | H67: https://www.google.com/maps/search/?api=1&query=LEILA%20HOUSE&query_place_id=ChIJixw26Y4ZQjERbTzKX6baQHU | I67: 31
B68: Tổng nhóm | C68: =SUM(C57:C67) -> 8000
A70: Nhóm 27 | B70: Mì Quảng Sứa Hồng Nga | C70: 525 | D70: 4.9 | E70: 67 Yên Bái | F70: Hải Châu, Đà Nẵng | G70: Quán ăn tối | H70: https://www.google.com/maps/search/?api=1&query=M%C3%AC%20Qu%E1%BA%A3ng%20S%E1%BB%A9a%20H%E1%BB%93ng%20Nga&query_place_id=ChIJy-ZdbgAZQjERAbtPY7ogE8A | I70: 525
A71: Nhóm 27 | B71: Ayi Bistro (四川小馆) | C71: 525 | D71: 4.6 | E71: 04 - 06 Hoàng Văn Thụ | F71: Hai Chau, Da Nang | G71: Bánh mỳ | H71: https://www.google.com/maps/search/?api=1&query=Ayi%20Bistro%20(%E5%9B%9B%E5%B7%9D%E5%B0%8F%E9%A6%86)&query_place_id=ChIJ75mSSo4ZQjERmszStfTaYWE | I71: 525
A72: Nhóm 27 | B72: Tiệm Ăn Trong Hẻm | C72: 523 | D72: 4.9 | E72: 98/1 Thanh Thủy | F72: Hải Châu, Đà Nẵng | G72: Nhà hàng Hàn Quốc | H72: https://www.google.com/maps/search/?api=1&query=Ti%E1%BB%87m%20%C4%82n%20Trong%20H%E1%BA%BBm&query_place_id=ChIJx8yWMQAZQjERTQ3tyKqSy3w | I72: 523
A73: Nhóm 27 | B73: The Alley Đà Nẵng | C73: 523 | D73: 3.9 | E73: 64 Nguyễn Văn Linh | F73: Hai Chau, Da Nang | G73: Trà sữa | H73: https://www.google.com/maps/search/?api=1&query=The%20Alley%20%C4%90%C3%A0%20N%E1%BA%B5ng&query_place_id=ChIJH4BKFwAZQjERenSgB5-_5BE | I73: 523
A74: Nhóm 27 | B74: Da Nang Rooftop - Craft Beer | C74: 523 | D74: 4.8 | E74: Tầng thượng, 1B Lê Duẩn | F74: Hai Chau, Da Nang | G74: Rooftop bar | H74: https://www.google.com/maps/search/?api=1&query=Da%20Nang%20Rooftop%20-%20Craft%20Beer&query_place_id=ChIJVfASWIIZQjERu0LgRyExKcE | I74: 523
A75: Nhóm 27 | B75: Cơm Mẹ Anh - Cơm Ngon Đà Nẵng - Local Vietnamese Cuisine | C75: 521 | D75: 4.8 | E75: 82 Đ. 2 Tháng 9 | F75: Hai Chau, Da Nang | G75: Quán bánh mì | H75: https://www.google.com/maps/search/?api=1&query=C%C6%A1m%20M%E1%BA%B9%20Anh%20-%20C%C6%A1m%20Ngon%20%C4%90%C3%A0%20N%E1%BA%B5ng%20-%20Local%20Vietnamese%20Cuisine&query_place_id=ChIJFXYcJQAZQjERFLQIEqyTzJA | I75: 521
A76: Nhóm 27 | B76: Hải Sản Bếu - 161 Nguyễn Tất Thành | C76: 517 | D76: 4.6 | E76: 161 Nguyễn Tất Thành | F76: Hai Chau, Da Nang | G76: Quán sinh tố | H76: https://www.google.com/maps/search/?api=1&query=H%E1%BA%A3i%20S%E1%BA%A3n%20B%E1%BA%BFu%20-%20161%20Nguy%E1%BB%85n%20T%E1%BA%A5t%20Th%C3%A0nh&query_place_id=ChIJwbgsWewZQjERi6rhgkeld4w | I76: 517
A77: Nhóm 27 | B77: Nhà hàng Phố Biển | C77: 515 | D77: 3.9 | E77: 231 Nguyễn Tất Thành | F77: Hải Châu, Đà Nẵng | G77: Nhà hàng Việt Nam | H77: https://www.google.com/maps/search/?api=1&query=Nh%C3%A0%20h%C3%A0ng%20Ph%E1%BB%91%20Bi%E1%BB%83n&query_place_id=ChIJl9gnIEcYQjER22X2cNht1i0 | I77: 515
A78: Nhóm 27 | B78: Cơm Gà Gia Vĩnh - Hoàng Diệu | C78: 515 | D78: 4.3 | E78: 37 Hoàng Diệu | F78: Hai Chau, Da Nang | G78: Quán nhậu | H78: https://www.google.com/maps/search/?api=1&query=C%C6%A1m%20G%C3%A0%20Gia%20V%C4%A9nh%20-%20Ho%C3%A0ng%20Di%E1%BB%87u&query_place_id=ChIJ3WI4sDQYQjERWZeHyUTGGAk | I78: 515
A79: Nhóm 27 | B79: Nhóp Nhép Lẩu Nướng | C79: 514 | D79: 3.8 | E79: 45 Hải Phòng | F79: Hai Chau, Da Nang | G79: Quán nhậu | H79: https://www.google.com/maps/search/?api=1&query=Nh%C3%B3p%20Nh%C3%A9p%20L%E1%BA%A9u%20N%C6%B0%E1%BB%9Bng&query_place_id=ChIJ3bvTWMsZQjERs-0IvsvA_yU | I79: 514
A80: Nhóm 27 | B80: OMORI DON cơm bò chuẩn Nhật | C80: 514 | D80: 4.3 | E80: 40 Lê Đình Dương | F80: Hải Châu, Đà Nẵng | G80: restaurant | H80: https://www.google.com/maps/search/?api=1&query=OMORI%20DON%20c%C6%A1m%20b%C3%B2%20chu%E1%BA%A9n%20Nh%E1%BA%ADt&query_place_id=ChIJy1xkrv0ZQjERnq_oofzPnow | I80: 514
A81: Nhóm 27 | B81: Bun Huong Restaurant | C81: 508 | D81: 4 | E81: 229 Đống Đa | F81: Hai Chau, Da Nang | G81: Quán bánh mì | H81: https://www.google.com/maps/search/?api=1&query=Bun%20Huong%20Restaurant&query_place_id=ChIJu1OK8zcYQjERyLv0M85kHd4 | I81: 508
... A85: Nhóm 27 | B85: Quán Lẩu & Nướng Hà Nội | C85: 265 | D85: 4.8 | E85: 14 Trần Quốc Toản | F85: Hai Chau, Da Nang | G85: Quán bar | H85: https://www.google.com/maps/search/?api=1&query=Qu%C3%A1n%20L%E1%BA%A9u%20%26%20N%C6%B0%E1%BB%9Bng%20H%C3%A0%20N%E1%BB%99i&query_place_id=ChIJWxuB-zIYQjERfFG8dK8dv2k | I85: 265
B86: Tổng nhóm | C86: =SUM(C70:C85) -> 8000
A88: Nhóm 30 | B88: FIRGUN CORNER COFFEE | C88: 404 | D88: 4.5 | E88: 182 Bạch Đằng | F88: Hai Chau, Da Nang | G88: Quán cà phê | H88: https://www.google.com/maps/search/?api=1&query=FIRGUN%20CORNER%20COFFEE&query_place_id=ChIJleqq7rAZQjERgiXTCTxvNBc | I88: 404
A89: Nhóm 30 | B89: Ramen Ichibanken【Đà Nẵng】 | C89: 404 | D89: 4.9 | E89: 203 Phan Châu Trinh | F89: Hải Châu, Đà Nẵng | G89: Nhà hàng Nhật Bản | H89: https://www.google.com/maps/search/?api=1&query=Ramen%20Ichibanken%E3%80%90%C4%90%C3%A0%20N%E1%BA%B5ng%E3%80%91&query_place_id=ChIJb5FIKpYZQjERvCiqpgNa33g | I89: 404
A90: Nhóm 30 | B90: Cửa hàng Ăn uống Mậu Dịch 1986 | C90: 403 | D90: 4.3 | E90: 149 Hải Phòng | F90: Hai Chau, Da Nang | G90: Quán bánh mì | H90: https://www.google.com/maps/search/?api=1&query=C%C6%B0%CC%89a%20ha%CC%80ng%20%C4%82n%20u%C3%B4%CC%81ng%20M%C3%A2%CC%A3u%20Di%CC%A3ch%201986&query_place_id=ChIJp70YIDYYQjERt9C3dAHDqwQ | I90: 403
A91: Nhóm 30 | B91: United Bar | C91: 400 | D91: 4.3 | E91: 02 Nguyễn Chí Thanh | F91: Hai Chau, Da Nang | G91: Wine bar | H91: https://www.google.com/maps/search/?api=1&query=United%20Bar&query_place_id=ChIJqVih1zsYQjERKfc5l4iw-N8 | I91: 400
A92: Nhóm 30 | B92: Chicky Licky - Huỳnh Thúc Kháng | C92: 393 | D92: 4.8 | E92: 116 Huỳnh Thúc Kháng | F92: Hai Chau, Da Nang | G92: Quán kem | H92: https://www.google.com/maps/search/?api=1&query=Chicky%20Licky%20-%20Hu%E1%BB%B3nh%20Th%C3%BAc%20Kh%C3%A1ng&query_place_id=ChIJhYwSxy0ZQjERNP271OBidt4 | I92: 393
A93: Nhóm 30 | B93: Quán Bò Né Quốc Minh | C93: 392 | D93: 4.2 | E93: 28 Phan Đình Phùng | F93: Hải Châu, Đà Nẵng | G93: Quán ăn tối | H93: https://www.google.com/maps/search/?api=1&query=Qu%C3%A1n%20B%C3%B2%20N%C3%A9%20Qu%E1%BB%91c%20Minh&query_place_id=ChIJYa0jkTEYQjER-XENRLn1Q4w | I93: 392
A94: Nhóm 30 | B94: Bún Bò Huế Bà Thương | C94: 392 | D94: 4.1 | E94: 23 Trần Quốc Toản | F94: Hải Châu, Đà Nẵng | G94: Quán ăn tối | H94: https://www.google.com/maps/search/?api=1&query=B%C3%BAn%20B%C3%B2%20Hu%E1%BA%BF%20B%C3%A0%20Th%C6%B0%C6%A1ng&query_place_id=ChIJtZ-j_DIYQjERp4pBNhnHIww | I94: 392
A95: Nhóm 30 | B95: กิน กิน Kin Kin Thai Food - 339 Phan Châu Trinh | C95: 390 | D95: 4.1 | E95: 339 Phan Châu Trinh | F95: Hải Châu, Đà Nẵng | G95: restaurant | H95: https://www.google.com/maps/search/?api=1&query=%E0%B8%81%E0%B8%B4%E0%B8%99%20%E0%B8%81%E0%B8%B4%E0%B8%99%20Kin%20Kin%20Thai%20Food%20-%20339%20Phan%20Ch%C3%A2u%20Trinh&query_place_id=ChIJwQgqiKwZQjERfTgLIXkkFhs | I95: 390
A96: Nhóm 30 | B96: Chin Meshi Dragon | C96: 389 | D96: 4.3 | E96: 23 Thái Phiên | F96: Hai Chau, Da Nang | G96: Quán bar | H96: https://www.google.com/maps/search/?api=1&query=Chin%20Meshi%20Dragon&query_place_id=ChIJW6HP2DIYQjER9xONLNZS91w | I96: 389
A97: Nhóm 30 | B97: Trà sữa Cloudy | C97: 388 | D97: 4.7 | E97: 46 Đ. 2 Tháng 9 | F97: Hai Chau, Da Nang | G97: Quán trà sữa | H97: https://www.google.com/maps/search/?api=1&query=Tr%C3%A0%20s%E1%BB%AFa%20Cloudy&query_place_id=ChIJyQ61HwAZQjERY8r8tQD7g4U | I97: 388
A98: Nhóm 30 | B98: Mì Quảng Giao Thủy | C98: 385 | D98: 4.1 | E98: 1B Ba Đình | F98: Hải Châu, Đà Nẵng | G98: Quán mỳ | H98: https://www.google.com/maps/search/?api=1&query=M%C3%AC%20Qu%E1%BA%A3ng%20Giao%20Th%E1%BB%A7y&query_place_id=ChIJ12di-jkYQjERYzn5EoYEBIo | I98: 385
A99: Nhóm 30 | B99: Bún đậu Gia Di - Đống Đa | C99: 384 | D99: 4.2 | E99: 193 Đống Đa | F99: Hải Châu, Đà Nẵng | G99: Nhà hàng gia đình | H99: https://www.google.com/maps/search/?api=1&query=B%C3%BAn%20%C4%91%E1%BA%ADu%20Gia%20Di%20-%20%C4%90%E1%BB%91ng%20%C4%90a&query_place_id=ChIJt8TxSccZQjER8jJ0jZcRJ8I | I99: 384
... A109: Nhóm 30 | B109: cà phê huy hiệp | C109: 1 | D109: 5 | E109: 137 Lý Tự Trọng | F109: Hai Chau, Da Nang | G109: Coffee | H109: https://www.google.com/maps/search/?api=1&query=c%C3%A0%20ph%C3%AA%20huy%20hi%E1%BB%87p&query_place_id=ChIJsQ4LfQAZQjER46h8q9qMBTU | I109: 1
B110: Tổng nhóm | C110: =SUM(C88:C109) -> 8000
A112: Nhóm 35 | B112: SASI - Korean Food | C112: 204 | D112: 4 | E112: 63 Hùng Vương | F112: Hải Châu, Đà Nẵng | G112: Quán mỳ | H112: https://www.google.com/maps/search/?api=1&query=SASI%20-%20Korean%20Food&query_place_id=ChIJDyn9JEoYQjEReN_ZzD5YZ7M | I112: 204
A113: Nhóm 35 | B113: Lẩu Tôm Bầu - 17 Đống Đa | C113: 204 | D113: 4.1 | E113: 17 Đống Đa | F113: Hai Chau, Da Nang | G113: Quán nhậu | H113: https://www.google.com/maps/search/?api=1&query=L%E1%BA%A9u%20T%C3%B4m%20B%E1%BA%A7u%20-%2017%20%C4%90%E1%BB%91ng%20%C4%90a&query_place_id=ChIJN8tRHgAZQjEREbKdTkkpnSM | I113: 204
A114: Nhóm 35 | B114: Quán chay Thiện Duyên | C114: 203 | D114: 4.4 | E114: 308 Hoàng Diệu | F114: Hai Chau, Da Nang | G114: Quán bánh mì | H114: https://www.google.com/maps/search/?api=1&query=Qu%C3%A1n%20chay%20Thi%E1%BB%87n%20Duy%C3%AAn&query_place_id=ChIJVXxDg8kZQjERwO2Ty7Ml4rE | I114: 203
A115: Nhóm 35 | B115: Storii Coffee | C115: 201 | D115: 5 | E115: 76 Hoàng Văn Thụ | F115: Hai Chau, Da Nang | G115: Coffee shop | H115: https://www.google.com/maps/search/?api=1&query=Storii%20Coffee&query_place_id=ChIJNaLuJgAZQjERR8XriqezEzw | I115: 201
A116: Nhóm 35 | B116: QUÁN HẢI SẢN 239 - BIA HƠI HÀ NỘI - CƠ SỞ 3 | C116: 201 | D116: 4.8 | E116: 173 Nguyễn Chí Thanh | F116: Hải Châu, Đà Nẵng | G116: Nhà hàng hải sản | H116: https://www.google.com/maps/search/?api=1&query=QU%C3%81N%20H%E1%BA%A2I%20S%E1%BA%A2N%20239%20-%20BIA%20H%C6%A0I%20H%C3%80%20N%E1%BB%98I%20-%20C%C6%A0%20S%E1%BB%9E%203&query_place_id=ChIJJSv8QcoZQjER8Bg-l6syPMs | I116: 201
A117: Nhóm 35 | B117: Cơm Gà Gia Vĩnh - Lý Tự Trọng | C117: 200 | D117: 4.1 | E117: 129 Lý Tự Trọng | F117: Hải Châu, Đà Nẵng | G117: Nhà hàng gia đình | H117: https://www.google.com/maps/search/?api=1&query=C%C6%A1m%20G%C3%A0%20Gia%20V%C4%A9nh%20-%20L%C3%BD%20T%E1%BB%B1%20Tr%E1%BB%8Dng&query_place_id=ChIJz9l0eKgZQjERLpNFIEo_NZw | I117: 200
A118: Nhóm 35 | B118: Maru Food & Drinks | C118: 199 | D118: 4 | E118: Trần Bình Trọng | F118: Hai Chau, Da Nang | G118: Quán trà sữa | H118: https://www.google.com/maps/search/?api=1&query=Maru%20Food%20%26%20Drinks&query_place_id=ChIJl93xhDQYQjERYcvdAbxfh4Q | I118: 199
A119: Nhóm 35 | B119: Nhà Hàng Hồ Xanh - Hồ Xanh Restaurant | C119: 199 | D119: 3.9 | E119: K 1 Đỗ Quang | F119: Thanh Khe, Da Nang | G119: Quán nhậu | H119: https://www.google.com/maps/search/?api=1&query=Nh%C3%A0%20H%C3%A0ng%20H%E1%BB%93%20Xanh%20-%20H%E1%BB%93%20Xanh%20Restaurant&query_place_id=ChIJ37F4OvoZQjERcSRyXX_s91c | I119: 199
A120: Nhóm 35 | B120: Pizza 4P's Indochina Da Nang | C120: 199 | D120: 4.6 | E120: Indochina Riverside Towers, Tòa nhà, 74 Bạch Đằng | F120: Hai Chau, Da Nang | G120: Craft beer | H120: https://www.google.com/maps/search/?api=1&query=Pizza%204P's%20Indochina%20Da%20Nang&query_place_id=ChIJ85aPCoIZQjERPOxKuiXQJTU | I120: 199
...

Sheet Hiếu
A1: Nhóm | B1: title | C1: reviewsCount (max 1035) | D1: totalScore | E1: street | F1: state | G1: searchString | H1: url | I1: reviewsCount gốc
A2: Nhóm 4 | B2: Yen Yakiniku & Izakaya – Buffet Nướng Nhật Bản tại Đà Nẵng 38 Trần Quốc Toản | C2: 1035 | D2: 4.8 | E2: 38 Trần Quốc Toản | F2: Hai Chau, Da Nang | G2: Quán nhậu | H2: https://www.google.com/maps/search/?api=1&query=Yen%20Yakiniku%20%26%20Izakaya%20%E2%80%93%20Buffet%20N%C6%B0%E1%BB%9Bng%20Nh%E1%BA%ADt%20B%E1%BA%A3n%20t%E1%BA%A1i%20%C4%90%C3%A0%20N%E1%BA%B5ng%2038%20Tr%E1%BA%A7n%20Qu%E1%BB%91c%20To%E1%BA%A3n&query_place_id=ChIJZSsvT9QZQjERf-oLnsT1C3Y | I2: 3543
A3: Nhóm 4 | B3: Mì Quảng Ếch bếp Trang | C3: 1035 | D3: 4.4 | E3: 441 Ông Ích Khiêm | F3: Hải Châu, Đà Nẵng | G3: Quán mỳ | H3: https://www.google.com/maps/search/?api=1&query=M%C3%AC%20Qu%E1%BA%A3ng%20%E1%BA%BEch%20b%E1%BA%BFp%20Trang&query_place_id=ChIJHRmt7soZQjERhuei1xWj9Xs | I3: 3250
A4: Nhóm 4 | B4: Ơ Kìa - Seafood Restaurant | C4: 1035 | D4: 4.8 | E4: 7 Trần Phú | F4: Hai Chau, Da Nang | G4: Pub | H4: https://www.google.com/maps/search/?api=1&query=%C6%A0%20K%C3%ACa%20-%20Seafood%20Restaurant&query_place_id=ChIJfb2A754ZQjERwntwhqY2_nQ | I4: 3201
A5: Nhóm 4 | B5: McDonald's Nguyễn Văn Linh | C5: 1035 | D5: 4.6 | E5: Nguyễn Văn Linh | F5: Hải Châu, Đà Nẵng | G5: restaurant | H5: https://www.google.com/maps/search/?api=1&query=McDonald's%20Nguy%E1%BB%85n%20V%C4%83n%20Linh&query_place_id=ChIJwfmizD8ZQjERtLtHJBCmCDw | I5: 3199
A6: Nhóm 4 | B6: Sky36 Bar Da Nang | C6: 1035 | D6: 4.3 | E6: 34-36 Bạch Đằng | F6: Hai Chau, Da Nang | G6: Rooftop bar | H6: https://www.google.com/maps/search/?api=1&query=Sky36%20Bar%20Da%20Nang&query_place_id=ChIJFWBN5ToYQjERomaB5cZoEaY | I6: 3190
A7: Nhóm 4 | B7: CHÚ BI quán nướng | C7: 1035 | D7: 4.8 | E7: 48 Nguyễn Chí Thanh | F7: Hải Châu, Đà Nẵng | G7: Nhà hàng buffet | H7: https://www.google.com/maps/search/?api=1&query=CH%C3%9A%20BI%20qu%C3%A1n%20n%C6%B0%E1%BB%9Bng&query_place_id=ChIJNcPfRBYZQjERUk2d0LOhtrk | I7: 2961
A8: Nhóm 4 | B8: Phở Bắc Hải | C8: 1035 | D8: 4.3 | E8: 185 Trần Phú | F8: Hai Chau, Da Nang | G8: Wine bar | H8: https://www.google.com/maps/search/?api=1&query=Ph%E1%BB%9F%20B%E1%BA%AFc%20H%E1%BA%A3i&query_place_id=ChIJaRNc9zIYQjER-4clHGRQQZE | I8: 2950
A9: Nhóm 4 | B9: Hoa Lan Souvenir and Coffee Shop | C9: 731 | D9: 5 | E9: 260 Trần Phú | F9: Hai Chau, Da Nang | G9: Coffee shop | H9: https://www.google.com/maps/search/?api=1&query=Hoa%20Lan%20Souvenir%20and%20Coffee%20Shop&query_place_id=ChIJ4wFQqQIZQjERQ29Ifqzv7-k | I9: 731
A10: Nhóm 4 | B10: Jolie coffee & Tea | C10: 24 | D10: 3.5 | E10: 308 Đống Đa | F10: Hai Chau, Da Nang | G10: Coffee | H10: https://www.google.com/maps/search/?api=1&query=Jolie%20coffee%20%26%20Tea&query_place_id=ChIJM_JVflQZQjER1u0IN6tc70s | I10: 24
B11: Tổng nhóm | C11: =SUM(C2:C10) -> 8000
A13: Nhóm 5 | B13: Kaldi & More Coffee Shop | C13: 1035 | D13: 4.7 | E13: 29-31 Hùng Vương | F13: Hai Chau, Da Nang | G13: Coffee | H13: https://www.google.com/maps/search/?api=1&query=Kaldi%20%26%20More%20Coffee%20Shop&query_place_id=ChIJwX-lhoARQjERHzmrwtbKRns | I13: 2917
A14: Nhóm 5 | B14: Cardi Pizzeria Bạch Đằng: Premium Steak & Pizza | C14: 1035 | D14: 4.8 | E14: 124 Bạch Đằng | F14: Hai Chau, Da Nang | G14: Quán pizza | H14: https://www.google.com/maps/search/?api=1&query=Cardi%20Pizzeria%20B%E1%BA%A1ch%20%C4%90%E1%BA%B1ng%3A%20Premium%20Steak%20%26%20Pizza&query_place_id=ChIJnzTGGJMZQjER5GQkGX-COKg | I14: 2659
A15: Nhóm 5 | B15: Gypsy Rooftop Restaurant & Bar | C15: 1035 | D15: 4.9 | E15: 20 Đống Đa | F15: Hai Chau, Da Nang | G15: Beer club | H15: https://www.google.com/maps/search/?api=1&query=Gypsy%20Rooftop%20Restaurant%20%26%20Bar&query_place_id=ChIJ76XtSwwZQjERJapWgs-OVhQ | I15: 2586
A16: Nhóm 5 | B16: Nhà hàng Nhà Gỗ Việt Đà Nẵng | C16: 1035 | D16: 4.6 | E16: 49 Nguyễn Thái Học | F16: Hải Châu, Đà Nẵng | G16: Nhà hàng Việt Nam | H16: https://www.google.com/maps/search/?api=1&query=Nh%C3%A0%20h%C3%A0ng%20Nh%C3%A0%20G%E1%BB%97%20Vi%E1%BB%87t%20%C4%90%C3%A0%20N%E1%BA%B5ng&query_place_id=ChIJYytdRW4ZQjER6149Azrswq8 | I16: 2585
A17: Nhóm 5 | B17: Umi Izakaya | C17: 1035 | D17: 4.7 | E17: 91 Hoàng Văn Thụ | F17: Hai Chau, Da Nang | G17: Quán bar | H17: https://www.google.com/maps/search/?api=1&query=Umi%20Izakaya&query_place_id=ChIJtQe0gqIZQjERwOyKwcOpNqA | I17: 2520
A18: Nhóm 5 | B18: Devis bakery | C18: 1035 | D18: 5 | E18: 60 Nguyễn Thái Học | F18: Hai Chau, Da Nang | G18: Tiệm bánh | H18: https://www.google.com/maps/search/?api=1&query=Devis%20bakery&query_place_id=ChIJ7xQxgxgZQjER9pYz4UOV0EY | I18: 2381
A19: Nhóm 5 | B19: Thai Market Restaurant - Yên Bái | C19: 1035 | D19: 4.4 | E19: 124 Yên Bái | F19: Hải Châu, Đà Nẵng | G19: Quán ăn tối | H19: https://www.google.com/maps/search/?api=1&query=Thai%20Market%20Restaurant%20-%20Y%C3%AAn%20B%C3%A1i&query_place_id=ChIJ6_TBIzMYQjER41Feg1SiLVY | I19: 2319
A20: Nhóm 5 | B20: IKIGAI . garden . cafe | C20: 726 | D20: 4.2 | E20: 60 Nguyễn Chí Thanh | F20: Hai Chau, Da Nang | G20: Quán sinh tố | H20: https://www.google.com/maps/search/?api=1&query=IKIGAI%20.%20garden%20.%20cafe&query_place_id=ChIJedpeSI4ZQjERYqZQdHBbz5E | I20: 726
A21: Nhóm 5 | B21: Cá Nục Cuốn Rau Muống | C21: 29 | D21: 2.8 | E21: 118 Huỳnh Thúc Kháng | F21: Hải Châu, Đà Nẵng | G21: Nhà hàng Việt Nam | H21: https://www.google.com/maps/search/?api=1&query=C%C3%A1%20N%E1%BB%A5c%20Cu%E1%BB%91n%20Rau%20Mu%E1%BB%91ng&query_place_id=ChIJnTjW3ssZQjEROc1qHIzL2xc | I21: 29
B22: Tổng nhóm | C22: =SUM(C13:C21) -> 8000
A24: Nhóm 12 | B24: The Joy Cafe | C24: 1035 | D24: 4.9 | E24: 7 Nguyễn Thái Học | F24: Hai Chau, Da Nang | G24: Cafe | H24: https://www.google.com/maps/search/?api=1&query=The%20Joy%20Cafe&query_place_id=ChIJl6bSFKAZQjERDdamCBNpBig | I24: 1511
A25: Nhóm 12 | B25: Xuyên Sushi - Đà Nẵng Cơ Sở 1 | C25: 1035 | D25: 4.7 | E25: Phan Châu Trinh/329A Bình Hiên | F25: Hải Châu, Đà Nẵng | G25: restaurant | H25: https://www.google.com/maps/search/?api=1&query=Xuy%C3%AAn%20Sushi%20-%20%C4%90%C3%A0%20N%E1%BA%B5ng%20C%C6%A1%20S%E1%BB%9F%201&query_place_id=ChIJD2KF7jEZQjERFNLDyHE50X8 | I25: 1507
A26: Nhóm 12 | B26: Nhà Hàng Chay Ngọc Chi - Vegetarian Restaurant Michelin guide 2025 | C26: 1035 | D26: 4.6 | E26: 202 Hoàng Diệu | F26: Hai Chau, Da Nang | G26: Pub | H26: https://www.google.com/maps/search/?api=1&query=Nh%C3%A0%20H%C3%A0ng%20Chay%20Ng%E1%BB%8Dc%20Chi%20-%20Vegetarian%20Restaurant%20Michelin%20guide%202025&query_place_id=ChIJPwlvPjMYQjERE56T1OCbYpM | I26: 1498
A27: Nhóm 12 | B27: LUNA Pub | C27: 1035 | D27: 4.4 | E27: 9A Trần Phú | F27: Hai Chau, Da Nang | G27: Wine bar | H27: https://www.google.com/maps/search/?api=1&query=LUNA%20Pub&query_place_id=ChIJ_5cPdjsYQjERLVVya-SBx24 | I27: 1497
A28: Nhóm 12 | B28: Highlands Coffee Hoang Anh Gia Lai | C28: 1035 | D28: 4.2 | E28: 115 Nguyễn Văn Linh | F28: Hải Châu, Đà Nẵng | G28: Quán ăn sáng | H28: https://www.google.com/maps/search/?api=1&query=Highlands%20Coffee%20Hoang%20Anh%20Gia%20Lai&query_place_id=ChIJ4ZJeS8oZQjERzAlK2SZaZaA | I28: 1492
A29: Nhóm 12 | B29: Chè Xuân Trang - cs 1 | C29: 1035 | D29: 4.1 | E29: 31 Lê Duẩn | F29: Hai Chau, Da Nang | G29: Quán chè | H29: https://www.google.com/maps/search/?api=1&query=Che%CC%80%20Xu%C3%A2n%20Trang%20-%20cs%201&query_place_id=ChIJ--T9ODEYQjERsbP55nVTym0 | I29: 1478
A30: Nhóm 12 | B30: Quán Phú Hồng | C30: 1035 | D30: 4.8 | E30: 19 Yên Bái | F30: Hải Châu, Đà Nẵng | G30: Quán ăn tối | H30: https://www.google.com/maps/search/?api=1&query=Qu%C3%A1n%20Phu%CC%81%20H%C3%B4%CC%80ng&query_place_id=ChIJ3xzmKjIYQjERKrkpxfu1R-Y | I30: 1478
A31: Nhóm 12 | B31: Trạm Ốc | C31: 694 | D31: 4.9 | E31: Hoàng Diệu/338/14 Bình Hiên | F31: Hai Chau, Da Nang | G31: Quán bar | H31: https://www.google.com/maps/search/?api=1&query=Tr%E1%BA%A1m%20%E1%BB%90c&query_place_id=ChIJCRvUiqYZQjERhzBUP7NWgmk | I31: 694
A32: Nhóm 12 | B32: Mì Tiều Châu | C32: 61 | D32: 4.6 | E32: 81 Thái Phiên | F32: Hải Châu, Đà Nẵng | G32: Nhà hàng Trung Quốc | H32: https://www.google.com/maps/search/?api=1&query=M%C3%AC%20Ti%E1%BB%81u%20Ch%C3%A2u&query_place_id=ChIJ-xCOTAAZQjERx4KPuNm76uw | I32: 61
B33: Tổng nhóm | C33: =SUM(C24:C32) -> 8000
A35: Nhóm 13 | B35: PER Korean food 2 | C35: 1035 | D35: 4.8 | E35: 204 Trần Phú | F35: Hải Châu, Đà Nẵng | G35: Quán ăn tối | H35: https://www.google.com/maps/search/?api=1&query=PER%20Korean%20food%202&query_place_id=ChIJ5auxl7QZQjER-3drr1-un8I | I35: 1465
A36: Nhóm 13 | B36: Phê La - Nguyễn Văn Linh, Đà Nẵng | C36: 1035 | D36: 4.3 | E36: 35 - 41 Nguyễn Văn Linh | F36: Hai Chau, Da Nang | G36: Cửa hàng bánh ngọt | H36: https://www.google.com/maps/search/?api=1&query=Ph%C3%AA%20La%20-%20Nguy%C3%AA%CC%83n%20V%C4%83n%20Linh%2C%20%C4%90%C3%A0%20N%E1%BA%B5ng&query_place_id=ChIJt5mYvvwZQjERec2rBUXL57A | I36: 1443
A37: Nhóm 13 | B37: Chè Liên Desserts | C37: 1035 | D37: 4.1 | E37: 175 Hải Phòng | F37: Thanh Khe, Da Nang | G37: Quán chè | H37: https://www.google.com/maps/search/?api=1&query=Ch%C3%A8%20Li%C3%AAn%20Desserts&query_place_id=ChIJJRvF6kkYQjERxtXYO1fCZCY | I37: 1434
A38: Nhóm 13 | B38: Bikini Bottom Express Pink Church | C38: 1035 | D38: 4.7 | E38: 154 Trần Phú | F38: Hải Châu, Đà Nẵng | G38: restaurant | H38: https://www.google.com/maps/search/?api=1&query=Bikini%20Bottom%20Express%20Pink%20Church&query_place_id=ChIJ7Qa_GAAZQjERwDheIFSvF2c | I38: 1424
A39: Nhóm 13 | B39: KOI Thé Nguyễn Văn Linh | C39: 1035 | D39: 4.5 | E39: 87 Nguyễn Văn Linh | F39: Hai Chau, Da Nang | G39: Trà sữa | H39: https://www.google.com/maps/search/?api=1&query=KOI%20Th%C3%A9%20Nguy%E1%BB%85n%20V%C4%83n%20Linh&query_place_id=ChIJz9j72agZQjERNYhRtw1ahGo | I39: 1414
A40: Nhóm 13 | B40: PhiPhi Sushi | C40: 1035 | D40: 4.7 | E40: 41 Lê Hồng Phong | F40: Hai Chau, Da Nang | G40: Quán nhậu | H40: https://www.google.com/maps/search/?api=1&query=PhiPhi%20Sushi&query_place_id=ChIJcQ0Qs0kYQjERDxit3A23Ggc | I40: 1402
A41: Nhóm 13 | B41: BOK JJAM PPONG | C41: 1035 | D41: 4.8 | E41: 92a Trần Phú | F41: Hải Châu, Đà Nẵng | G41: Nhà hàng Hàn Quốc | H41: https://www.google.com/maps/search/?api=1&query=BOK%20JJAM%20PPONG&query_place_id=ChIJDWu4c_MZQjEREd-mkCKxnU4 | I41: 1393
A42: Nhóm 13 | B42: Bánh Mì Kim | C42: 694 | D42: 4.8 | E42: 16/4 Hùng Vương | F42: Hai Chau, Da Nang | G42: Bánh mỳ | H42: https://www.google.com/maps/search/?api=1&query=B%C3%A1nh%20M%C3%AC%20Kim&query_place_id=ChIJ35a1SGUZQjER2T5aqZ-6vjU | I42: 694
A43: Nhóm 13 | B43: Tiệm ăn Luckki | C43: 61 | D43: 3.7 | E43: 206/5 Đống Đa | F43: Hai Chau, Da Nang | G43: Quán nhậu | H43: https://www.google.com/maps/search/?api=1&query=Ti%E1%BB%87m%20%C4%83n%20Luckki&query_place_id=ChIJ3a_cwWkZQjERo4bs9gHuIpg | I43: 61
B44: Tổng nhóm | C44: =SUM(C35:C43) -> 8000
A46: Nhóm 20 | B46: Havana Phan Chu Trinh Đà Nẵng | C46: 941 | D46: 4.9 | E46: Địa chỉ: 261, 263 Phan Châu Trinh | F46: Hai Chau, Da Nang | G46: Club | H46: https://www.google.com/maps/search/?api=1&query=Havana%20Phan%20Chu%20Trinh%20%C4%90%C3%A0%20N%E1%BA%B5ng&query_place_id=ChIJ9yiTjMsZQjERgrmIRi9_l8U | I46: 941
A47: Nhóm 20 | B47: Trà sữa Money | C47: 941 | D47: 3.9 | E47: 17 Nguyễn Du | F47: Hai Chau, Da Nang | G47: Quán trà sữa | H47: https://www.google.com/maps/search/?api=1&query=Tr%C3%A0%20s%E1%BB%AFa%20Money&query_place_id=ChIJa_RtpjsYQjERAE43ix3t-t8 | I47: 941
A48: Nhóm 20 | B48: TMORE 24/7 | C48: 930 | D48: 4.3 | E48: 76 Lê Đình Dương | F48: Hai Chau, Da Nang | G48: Cửa hàng bánh ngọt | H48: https://www.google.com/maps/search/?api=1&query=TMORE%2024%2F7&query_place_id=ChIJh-AQEj8ZQjERYUAmgIbo8Hs | I48: 930
A49: Nhóm 20 | B49: Maju Top Class Bar - lounge | C49: 930 | D49: 5 | E49: 85 Nguyễn Chí Thanh | F49: Hai Chau, Da Nang | G49: Lounge bar | H49: https://www.google.com/maps/search/?api=1&query=Maju%20Top%20Class%20Bar%20-%20lounge&query_place_id=ChIJ6e7t67oZQjERLcf4KcgElEc | I49: 930
A50: Nhóm 20 | B50: Bún Chả cá Ông Tạ | C50: 915 | D50: 4 | E50: 113A Nguyễn Chí Thanh | F50: Hai Chau, Da Nang | G50: Quán nhậu | H50: https://www.google.com/maps/search/?api=1&query=B%C3%BAn%20Ch%E1%BA%A3%20c%C3%A1%20%C3%94ng%20T%E1%BA%A1&query_place_id=ChIJu96QJzEYQjERULs7SbdN0_A | I50: 915
A51: Nhóm 20 | B51: Sultan Istanbul Kebab Da Nang | Halal Turkish Food | C51: 912 | D51: 4.6 | E51: 250 Trần Phú | F51: Hải Châu, Đà Nẵng | G51: restaurant | H51: https://www.google.com/maps/search/?api=1&query=Sultan%20Istanbul%20Kebab%20Da%20Nang%20%7C%20Halal%20Turkish%20Food&query_place_id=ChIJ8TfBbO8ZQjER71nDeSG2tfc | I51: 912
A52: Nhóm 20 | B52: Bánh mỳ Bà Lan | C52: 911 | D52: 4.1 | E52: 62 Trưng Nữ Vương | F52: Hải Châu, Đà Nẵng | G52: restaurant | H52: https://www.google.com/maps/search/?api=1&query=B%C3%A1nh%20m%E1%BB%B3%20Ba%CC%80%20Lan&query_place_id=ChIJ25InOcwZQjERnYokrniHXTQ | I52: 911
A53: Nhóm 20 | B53: 자갈집 Gravel House BBQ Restaurant Da Nang | C53: 908 | D53: 4.9 | E53: 91 Trần Phú | F53: Hải Châu, Đà Nẵng | G53: Nhà hàng Hàn Quốc | H53: https://www.google.com/maps/search/?api=1&query=%EC%9E%90%EA%B0%88%EC%A7%91%20Gravel%20House%20BBQ%20Restaurant%20Da%20Nang&query_place_id=ChIJ3zZxegAZQjERNWhbUjPscdY | I53: 908
A54: Nhóm 20 | B54: byC. café and brunch | C54: 612 | D54: 4.7 | E54: 07 Nguyễn Du | F54: Hai Chau, Da Nang | G54: Pub | H54: https://www.google.com/maps/search/?api=1&query=byC.%20caf%C3%A9%20and%20brunch&query_place_id=ChIJI7DY6FAZQjERPfN1WR9CoyA | I54: 612
B55: Tổng nhóm | C55: =SUM(C46:C54) -> 8000
A57: Nhóm 21 | B57: indigo coffee | C57: 900 | D57: 4.9 | E57: 177 Trần Phú | F57: Hai Chau, Da Nang | G57: Coffee | H57: https://www.google.com/maps/search/?api=1&query=indigo%20coffee&query_place_id=ChIJv3c7dgAZQjERq-KhMJT99U4 | I57: 900
A58: Nhóm 21 | B58: Bếp Của Ngoại | C58: 893 | D58: 4.5 | E58: 136b Yên Bái | F58: Hải Châu, Đà Nẵng | G58: Quán ăn tối | H58: https://www.google.com/maps/search/?api=1&query=B%E1%BA%BFp%20C%E1%BB%A7a%20Ngo%E1%BA%A1i&query_place_id=ChIJZbBJytwZQjER4Ip26M8B0ww | I58: 893
A59: Nhóm 21 | B59: Lũ Noodle | C59: 884 | D59: 4.9 | E59: 261-263 Nguyễn Chí Thanh | F59: Hải Châu, Đà Nẵng | G59: Nhà hàng Trung Quốc | H59: https://www.google.com/maps/search/?api=1&query=L%C5%A9%20Noodle&query_place_id=ChIJd9itBwAZQjERTsyg1ayNR6s | I59: 884
A60: Nhóm 21 | B60: REDEN RESTAURANT | C60: 876 | D60: 4.7 | E60: 10 Nguyễn Chí Thanh | F60: Hai Chau, Da Nang | G60: Wine bar | H60: https://www.google.com/maps/search/?api=1&query=REDEN%20RESTAURANT&query_place_id=ChIJzztI_nUZQjER96Lozo1FAJc | I60: 876
A61: Nhóm 21 | B61: Àla Cafe | C61: 861 | D61: 4.6 | E61: 113/27 Nguyễn Chí Thanh | F61: Hai Chau, Da Nang | G61: Quán bar | H61: https://www.google.com/maps/search/?api=1&query=%C3%80la%20Cafe&query_place_id=ChIJ6YzGFvEZQjERtj5MGs3Pj2Q | I61: 861
A62: Nhóm 21 | B62: Highlands Coffee Tran Phu Da Nang | C62: 857 | D62: 4.1 | E62: 216 Trần Phú | F62: Hai Chau, Da Nang | G62: Quán cà phê | H62: https://www.google.com/maps/search/?api=1&query=Highlands%20Coffee%20Tran%20Phu%20Da%20Nang&query_place_id=ChIJ-_eMMPAZQjERXhS8sd4507Q | I62: 857
A63: Nhóm 21 | B63: BonPas Bakery & Coffee | C63: 851 | D63: 4.3 | E63: 21 Ng. Gia Tự | F63: Hai Chau, Da Nang | G63: Cửa hàng bánh ngọt | H63: https://www.google.com/maps/search/?api=1&query=BonPas%20Bakery%20%26%20Coffee&query_place_id=ChIJFxpIcDYYQjERA9am1qqeNnA | I63: 851
A64: Nhóm 21 | B64: 다낭 라운지 베트남플레이 | C64: 845 | D64: 4.9 | E64: 60 Hùng Vương | F64: Hai Chau, Da Nang | G64: Quán bar | H64: https://www.google.com/maps/search/?api=1&query=%EB%8B%A4%EB%82%AD%20%EB%9D%BC%EC%9A%B4%EC%A7%80%20%EB%B2%A0%ED%8A%B8%EB%82%A8%ED%94%8C%EB%A0%88%EC%9D%B4&query_place_id=ChIJc4plWPEZQjERgGVczDlEMw4 | I64: 845
A65: Nhóm 21 | B65: Cong Caphe | C65: 838 | D65: 4.4 | E65: 23 Lý Tự Trọng | F65: Hai Chau, Da Nang | G65: Quán bar | H65: https://www.google.com/maps/search/?api=1&query=Cong%20Caphe&query_place_id=ChIJbbryERkZQjERc8bjJ3vLFT0 | I65: 838
A66: Nhóm 21 | B66: Ca ca Nail Bar (베트남 다낭 카가 네일) | C66: 194 | D66: 5 | E66: 221 Hoàng Diệu | F66: Hai Chau, Da Nang | G66: Quán bar | H66: https://www.google.com/maps/search/?api=1&query=Ca%20ca%20Nail%20Bar%20(%E1%84%87%E1%85%A6%E1%84%90%E1%85%B3%E1%84%82%E1%85%A1%E1%86%B7%20%E1%84%83%E1%85%A1%E1%84%82%E1%85%A1%E1%86%BC%20%EC%B9%B4%EA%B0%80%20%E1%84%82%E1%85%A6%E1%84%8B%E1%85%B5%E1%86%AF)&query_place_id=ChIJm-lWt0IZQjERYBrxCPrMSso | I66: 194
A67: Nhóm 21 | B67: Kết Coffee & More | C67: 1 | D67: 5 | E67: 119A Ông Ích Khiêm | F67: Hai Chau, Da Nang | G67: Coffee | H67: https://www.google.com/maps/search/?api=1&query=K%E1%BA%BFt%20Coffee%20%26%20More&query_place_id=ChIJ1bsrV4YZQjERFx57zkC4qyE | I67: 1
B68: Tổng nhóm | C68: =SUM(C57:C67) -> 8000
A70: Nhóm 28 | B70: DANA BUFFET | C70: 501 | D70: 4.2 | E70: 56 Nguyễn Chí Thanh | F70: Hai Chau, Da Nang | G70: Quán bar | H70: https://www.google.com/maps/search/?api=1&query=DANA%20BUFFET&query_place_id=ChIJj7dAtzAYQjER6clbstYpSUE | I70: 501
A71: Nhóm 28 | B71: Nhà hàng Hai Cử | C71: 500 | D71: 4 | E71: 63 Yên Bái | F71: Hải Châu, Đà Nẵng | G71: Quán ăn tối | H71: https://www.google.com/maps/search/?api=1&query=Nh%C3%A0%20h%C3%A0ng%20Hai%20C%E1%BB%AD&query_place_id=ChIJ8cqHGTMYQjERU0gT5dridKc | I71: 500
A72: Nhóm 28 | B72: UDON TEN | C72: 489 | D72: 4.4 | E72: 70 Lê Hồng Phong | F72: Hai Chau, Da Nang | G72: Quán bar | H72: https://www.google.com/maps/search/?api=1&query=UDON%20TEN&query_place_id=ChIJB1VEGIMZQjER3I7Z93ZmhyE | I72: 489
A73: Nhóm 28 | B73: Tàu hủ Xe Lam | C73: 486 | D73: 4.1 | E73: 176 Trần Phú | F73: Hải Châu, Đà Nẵng | G73: Quán ăn tối | H73: https://www.google.com/maps/search/?api=1&query=T%C3%A0u%20h%E1%BB%A7%20Xe%20Lam&query_place_id=ChIJ2aXl5jIYQjERFvBRr0GwTwg | I73: 486
A74: Nhóm 28 | B74: TIỆM CƠM CHÚ TÈO CS2 - Cơm niêu singapore | C74: 485 | D74: 4.8 | E74: 52 Lê Đình Dương | F74: Hai Chau, Da Nang | G74: Quán kem | H74: https://www.google.com/maps/search/?api=1&query=TI%E1%BB%86M%20C%C6%A0M%20CH%C3%9A%20T%C3%88O%20CS2%20-%20C%C6%A1m%20ni%C3%AAu%20singapore&query_place_id=ChIJh2XP8C4ZQjER8bNhIwAw42Q | I74: 485
A75: Nhóm 28 | B75: Bún chả cá Bà Phiến (Bà Thừa) | C75: 484 | D75: 4.3 | E75: 63 Lê Hồng Phong | F75: Hải Châu, Đà Nẵng | G75: Nhà hàng hải sản | H75: https://www.google.com/maps/search/?api=1&query=B%C3%BAn%20ch%E1%BA%A3%20c%C3%A1%20B%C3%A0%20Phi%E1%BA%BFn%20(B%C3%A0%20Th%E1%BB%ABa)&query_place_id=ChIJj-ieb8oZQjER3hv6nLnFync | I75: 484
A76: Nhóm 28 | B76: The PowerHouse - Nhà hát lớn | C76: 480 | D76: 4.6 | E76: 87-93 Nguyễn Thái Học | F76: Hai Chau, Da Nang | G76: Coffee | H76: https://www.google.com/maps/search/?api=1&query=The%20PowerHouse%20-%20Nh%C3%A0%20h%C3%A1t%20l%E1%BB%9Bn&query_place_id=ChIJh1t3DwAZQjERBMg5CQP1D00 | I76: 480
A77: Nhóm 28 | B77: Outta da Blue Đà Nẵng - Danang Specialty Coffee Shop - 다낭 스페셜티 커피 전문점 - ダナン・スペシャルティコーヒーショップ - 岘港精品咖啡店 | C77: 479 | D77: 4.9 | E77: 66 Pasteur | F77: Hai Chau, Da Nang | G77: Coffee shop | H77: https://www.google.com/maps/search/?api=1&query=Outta%20da%20Blue%20%C4%90%C3%A0%20N%E1%BA%B5ng%20-%20Danang%20Specialty%20Coffee%20Shop%20-%20%EB%8B%A4%EB%82%AD%20%EC%8A%A4%ED%8E%98%EC%85%9C%ED%8B%B0%20%EC%BB%A4%ED%94%BC%20%EC%A0%84%EB%AC%B8%EC%A0%90%20-%20%E3%83%80%E3%83%8A%E3%83%B3%E3%83%BB%E3%82%B9%E3%83%9A%E3%82%B7%E3%83%A3%E3%83%AB%E3%83%86%E3%82%A3%E3%82%B3%E3%83%BC%E3%83%92%E3%83%BC%E3%82%B7%E3%83%A7%E3%83%83%E3%83%97%20-%20%E5%B2%98%E6%B8%AF%E7%B2%BE%E5%93%81%E5%92%96%E5%95%A1%E5%BA%97&query_place_id=ChIJD1lJegAZQjERIye70XzxAXk | I77: 479
A78: Nhóm 28 | B78: Bonchon Chicken Da Nang - 12 Lê Hồng Phong | C78: 472 | D78: 4.5 | E78: 12 Lê Hồng Phong | F78: Hải Châu, Đà Nẵng | G78: Nhà hàng Nhật Bản | H78: https://www.google.com/maps/search/?api=1&query=Bonchon%20Chicken%20Da%20Nang%20-%2012%20L%C3%AA%20H%E1%BB%93ng%20Phong&query_place_id=ChIJa1fuyqMZQjERtpBeO_uBJTI | I78: 472
A79: Nhóm 28 | B79: Nhân Méo | C79: 471 | D79: 4.1 | E79: 138 Đ. 3 Tháng 2 | F79: Hải Châu, Đà Nẵng | G79: restaurant | H79: https://www.google.com/maps/search/?api=1&query=Nh%C3%A2n%20M%C3%A9o&query_place_id=ChIJLyRYOz4YQjERGTSPdZ1qhP8 | I79: 471
A80: Nhóm 28 | B80: Quán thịt nướng 88 POCHA | C80: 470 | D80: 4.8 | E80: lô A24 Đ. 2 Tháng 9 | F80: Hoa Cuong, Da Nang | G80: Quán bar | H80: https://www.google.com/maps/search/?api=1&query=Qu%C3%A1n%20th%E1%BB%8Bt%20n%C6%B0%E1%BB%9Bng%2088%20POCHA&query_place_id=ChIJ45ZyKgAZQjER5u9A6S_i7v0 | I80: 470
A81: Nhóm 28 | B81: Bánh Canh Cua - Quân Nguyễn | C81: 470 | D81: 4.2 | E81: 24 Ông Ích Khiêm | F81: Hải Châu, Đà Nẵng | G81: Quán ăn sáng | H81: https://www.google.com/maps/search/?api=1&query=B%C3%A1nh%20Canh%20Cua%20-%20Qu%C3%A2n%20Nguy%E1%BB%85n&query_place_id=ChIJYVnIpUMZQjERQmVUDJtpTDE | I81: 470
... A87: Nhóm 28 | B87: Cà phê BIBI | C87: 1 | D87: 5 | E87: 51 Cao Thắng | F87: Hai Chau, Da Nang | G87: Coffee | H87: https://www.google.com/maps/search/?api=1&query=C%C3%A0%20ph%C3%AA%20BIBI&query_place_id=ChIJu4ZtUQAZQjEReTqDDWPbsDs | I87: 1
B88: Tổng nhóm | C88: =SUM(C70:C87) -> 8000
A90: Nhóm 29 | B90: Quán Bánh xèo nem lụi Bà Ngọc (Từ năm 1977) | C90: 445 | D90: 3.7 | E90: 228 Đống Đa | F90: Hải Châu, Đà Nẵng | G90: Nhà hàng Việt Nam | H90: https://www.google.com/maps/search/?api=1&query=Qu%C3%A1n%20B%C3%A1nh%20x%C3%A8o%20nem%20l%E1%BB%A5i%20B%C3%A0%20Ng%E1%BB%8Dc%20(T%E1%BB%AB%20n%C4%83m%201977)&query_place_id=ChIJqfj7UTgYQjERN61NMDftSGU | I90: 445
A91: Nhóm 29 | B91: Kem Dừa Mã Lai | C91: 441 | D91: 4.8 | E91: 47 Yên Bái | F91: Hai Chau, Da Nang | G91: Quán kem | H91: https://www.google.com/maps/search/?api=1&query=Kem%20D%E1%BB%ABa%20M%C3%A3%20Lai&query_place_id=ChIJhXaU6YYZQjERPkQWFGWcUiM | I91: 441
A92: Nhóm 29 | B92: Vin de Soleil Restaurant | C92: 441 | D92: 4.8 | E92: Nguyễn Tất Thành | F92: Hai Chau, Da Nang | G92: Cafe | H92: https://www.google.com/maps/search/?api=1&query=Vin%20de%20Soleil%20Restaurant&query_place_id=ChIJBZ9UB0YYQjERJBTN2CVn2bY | I92: 441
A93: Nhóm 29 | B93: Bò né Khanh | C93: 436 | D93: 4.1 | E93: 41 Hoàng Văn Thụ | F93: Hai Chau, Da Nang | G93: Bánh mỳ | H93: https://www.google.com/maps/search/?api=1&query=B%C3%B2%20n%C3%A9%20Khanh&query_place_id=ChIJLzL4w8wZQjERLY_3S_W1BAU | I93: 436
A94: Nhóm 29 | B94: 다낭과일집&빙수 Trái cây - Bingsu Đà Nẵng | C94: 435 | D94: 4.5 | E94: 162 Trần Phú | F94: Hai Chau, Da Nang | G94: Tiệm bánh | H94: https://www.google.com/maps/search/?api=1&query=%EB%8B%A4%EB%82%AD%EA%B3%BC%EC%9D%BC%EC%A7%91%26%EB%B9%99%EC%88%98%20Tr%C3%A1i%20c%C3%A2y%20-%20Bingsu%20%C4%90%C3%A0%20N%E1%BA%B5ng&query_place_id=ChIJp8ugMQAZQjERe2UVv4ciFPg | I94: 435
A95: Nhóm 29 | B95: Cake Crush | C95: 434 | D95: 4.6 | E95: 74 Trần Quốc Toản | F95: Hai Chau, Da Nang | G95: Cửa hàng bánh ngọt | H95: https://www.google.com/maps/search/?api=1&query=Cake%20Crush&query_place_id=ChIJkxsucjMYQjERshXXDqn_Pdk | I95: 434
A96: Nhóm 29 | B96: Nhà Hàng Thịt Nướng Nhật Bản Phổ Đình Yên Bái - Uraetei Yakiniku | C96: 434 | D96: 4.4 | E96: 104-106 Yên Bái | F96: Hải Châu, Đà Nẵng | G96: Quán ăn tối | H96: https://www.google.com/maps/search/?api=1&query=Nh%C3%A0%20H%C3%A0ng%20Th%E1%BB%8Bt%20N%C6%B0%E1%BB%9Bng%20Nh%E1%BA%ADt%20B%E1%BA%A3n%20Ph%E1%BB%95%20%C4%90%C3%ACnh%20Y%C3%AAn%20B%C3%A1i%20-%20Uraetei%20Yakiniku&query_place_id=ChIJ7TdlGDMYQjEREH43X8M6e7Y | I96: 434
A97: Nhóm 29 | B97: The Local Beans | Coffee - Roastery & co-Working Space – Da Nang | C97: 434 | D97: 4.3 | E97: 186 Phan Châu Trinh | F97: Hai Chau, Da Nang | G97: Coffee shop | H97: https://www.google.com/maps/search/?api=1&query=The%20Local%20Beans%20%7C%20Coffee%20-%20Roastery%20%26%20co-Working%20Space%20%E2%80%93%20Da%20Nang&query_place_id=ChIJZ-P8KgAZQjERSzFxeVWi-7Y | I97: 434
A98: Nhóm 29 | B98: DD WONDERLAND | C98: 433 | D98: 4.2 | E98: 78b Quang Trung | F98: Hai Chau, Da Nang | G98: Club đêm | H98: https://www.google.com/maps/search/?api=1&query=DD%20WONDERLAND&query_place_id=ChIJQWQVKr4ZQjERcafNnRyLelk | I98: 433
A99: Nhóm 29 | B99: Ốc Xinh Xinh | C99: 421 | D99: 4.5 | E99: 117 Huỳnh Thúc Kháng | F99: Hai Chau, Da Nang | G99: Bánh mỳ | H99: https://www.google.com/maps/search/?api=1&query=%E1%BB%90c%20Xinh%20Xinh&query_place_id=ChIJRRXBALoZQjERJzXSIJmDgIo | I99: 421
A100: Nhóm 29 | B100: GÀ NƯỚNG MẮM NHĨ NHẤT VỊ | C100: 417 | D100: 4.9 | E100: 271 Nguyễn Hoàng | F100: Hải Châu, Đà Nẵng | G100: Nhà hàng gia đình | H100: https://www.google.com/maps/search/?api=1&query=G%C3%80%20N%C6%AF%E1%BB%9ANG%20M%E1%BA%AEM%20NH%C4%A8%20NH%E1%BA%A4T%20V%E1%BB%8A&query_place_id=ChIJmf0p_hcZQjERuATEZd1LGz8 | I100: 417
A101: Nhóm 29 | B101: Bar Đồ Yêu - Authentic Vietnamese Cocktail | Best Cocktail Bar in Da Nang | C101: 417 | D101: 4.9 | E101: 87 Hoàng Văn Thụ | F101: Hai Chau, Da Nang | G101: Quán bar | H101: https://www.google.com/maps/search/?api=1&query=Bar%20%C4%90%E1%BB%93%20Y%C3%AAu%20-%20Authentic%20Vietnamese%20Cocktail%20%7C%20Best%20Cocktail%20Bar%20in%20Da%20Nang&query_place_id=ChIJZVLi0gEZQjERl6s0h2bqoK0 | I101: 417
... A108: Nhóm 29 | B108: Cơm gà Tam Kỳ Bà Nguyệt | C108: 347 | D108: 4.3 | E108: 49 Đường Lê Hồng Phong | F108: Hải Châu, Đà Nẵng | G108: Quán ăn tối | H108: https://www.google.com/maps/search/?api=1&query=C%C6%A1m%20ga%CC%80%20Tam%20K%E1%BB%B3%20Ba%CC%80%20Nguy%C3%AA%CC%A3t&query_place_id=ChIJjT3cicwZQjERY8vPSqJmMqw | I108: 347
B109: Tổng nhóm | C109: =SUM(C90:C108) -> 8000
A111: Nhóm 36 | B111: Seafood Cô Ly | C111: 164 | D111: 4.3 | E111: 148 Đ. 3 Tháng 2 | F111: Hải Châu, Đà Nẵng | G111: restaurant | H111: https://www.google.com/maps/search/?api=1&query=Seafood%20C%C3%B4%20Ly&query_place_id=ChIJiYtOnRUYQjERCu3THE8asJg | I111: 164
A112: Nhóm 36 | B112: Tiệm ăn 777 | C112: 164 | D112: 3.7 | E112: 37 Đống Đa | F112: Hải Châu, Đà Nẵng | G112: Quán ăn trưa | H112: https://www.google.com/maps/search/?api=1&query=Ti%E1%BB%87m%20%C4%83n%20777&query_place_id=ChIJo6ERpj4YQjER7pRjx-CnDsA | I112: 164
A113: Nhóm 36 | B113: Thuận Thành 297 Hoàng Diệu | C113: 164 | D113: 4.1 | E113: Hoàng Diệu/297 Bình Hiên | F113: Hai Chau, Da Nang | G113: Bánh mỳ | H113: https://www.google.com/maps/search/?api=1&query=Thu%E1%BA%ADn%20Th%C3%A0nh%20297%20Ho%C3%A0ng%20Di%E1%BB%87u&query_place_id=ChIJe7zJ6K0ZQjERdSp0Oo0fEqA | I113: 164
A114: Nhóm 36 | B114: Cao Lầu Hoài Phố | C114: 163 | D114: 4.3 | E114: 255 Nguyễn Chí Thanh | F114: Hai Chau, Da Nang | G114: Tiệm bánh | H114: https://www.google.com/maps/search/?api=1&query=Cao%20L%E1%BA%A7u%20Ho%C3%A0i%20Ph%E1%BB%91&query_place_id=ChIJ_TTYzCMZQjERqOAEci-_t74 | I114: 163
A115: Nhóm 36 | B115: Simple Candy Đà Nẵng | C115: 163 | D115: 4.9 | E115: 106 Nguyễn Văn Linh | F115: Hai Chau, Da Nang | G115: Cửa hàng bánh ngọt | H115: https://www.google.com/maps/search/?api=1&query=Simple%20Candy%20%C4%90%C3%A0%20N%E1%BA%B5ng&query_place_id=ChIJtTijY8YZQjERCYHdovwp8YQ | I115: 163
A116: Nhóm 36 | B116: Mộc Lam Yên 2 - 57 Trần Quốc Toản | C116: 163 | D116: 4.8 | E116: 57 Trần Quốc Toản | F116: Hải Châu, Đà Nẵng | G116: Nhà hàng hải sản | H116: https://www.google.com/maps/search/?api=1&query=M%E1%BB%99c%20Lam%20Y%C3%AAn%202%20-%2057%20Tr%E1%BA%A7n%20Qu%E1%BB%91c%20To%E1%BA%A3n&query_place_id=ChIJz_cqHAAZQjERW_dbC9mMOYc | I116: 163
A117: Nhóm 36 | B117: Tiệm Mỳ Ý Tasty By Len | C117: 162 | D117: 4.7 | E117: 49 Lê Lợi | F117: Hải Châu, Đà Nẵng | G117: Quán mỳ | H117: https://www.google.com/maps/search/?api=1&query=Ti%E1%BB%87m%20M%E1%BB%B3%20%C3%9D%20Tasty%20By%20Len&query_place_id=ChIJn4GYvTYZQjERwMsCtv0vYH0 | I117: 162
A118: Nhóm 36 | B118: DỪA BẾN TRE 196 | C118: 162 | D118: 4.4 | E118: 196 Bạch Đằng | F118: Hai Chau, Da Nang | G118: Tiệm bánh | H118: https://www.google.com/maps/search/?api=1&query=D%E1%BB%AAA%20B%E1%BA%BEN%20TRE%20196&query_place_id=ChIJgzksMVQZQjER38ehAHOlYGg | I118: 162
A119: Nhóm 36 | B119: An Lê Bakery - 08 Hải Phòng | C119: 162 | D119: 4.9 | E119: 08 Hải Phòng | F119: Hai Chau, Da Nang | G119: Cửa hàng bánh ngọt | H119: https://www.google.com/maps/search/?api=1&query=An%20L%C3%AA%20Bakery%20-%2008%20H%E1%BA%A3i%20Ph%C3%B2ng&query_place_id=ChIJVXfrN5cZQjERv_qA3nUVF4k | I119: 162
...

Sheet Tổng hợp
A1: Người | B1: Nhóm / acc | C1: Số địa điểm | D1: Tổng reviewsCount
A2: Người 1 | B2: Nhóm 1 | C2: 9 | D2: ='Người 1'!C11 -> 8000
A3: Người 1 | B3: Nhóm 8 | C3: 9 | D3: ='Người 1'!C22 -> 8000
A4: Người 1 | B4: Nhóm 9 | C4: 9 | D4: ='Người 1'!C33 -> 8000
A5: Người 1 | B5: Nhóm 16 | C5: 9 | D5: ='Người 1'!C44 -> 8000
A6: Người 1 | B6: Nhóm 17 | C6: 9 | D6: ='Người 1'!C55 -> 8000
A7: Người 1 | B7: Nhóm 24 | C7: 14 | D7: ='Người 1'!C71 -> 8000
A8: Người 1 | B8: Nhóm 25 | C8: 14 | D8: ='Người 1'!C87 -> 8000
A9: Người 1 | B9: Nhóm 32 | C9: 28 | D9: ='Người 1'!C117 -> 8000
A10: Người 1 | B10: Nhóm 33 | C10: 32 | D10: ='Người 1'!C151 -> 8000
A11: Người 1 | B11: Nhóm 40 | C11: 738 | D11: ='Người 1'!C891 -> 7764
A12: Người 2 | B12: Nhóm 2 | C12: 9 | D12: ='Trân'!C11 -> 8000
A13: Người 2 | B13: Nhóm 7 | C13: 9 | D13: ='Trân'!C22 -> 8000
A14: Người 2 | B14: Nhóm 10 | C14: 9 | D14: ='Trân'!C33 -> 8000
A15: Người 2 | B15: Nhóm 15 | C15: 9 | D15: ='Trân'!C44 -> 8000
A16: Người 2 | B16: Nhóm 18 | C16: 9 | D16: ='Trân'!C55 -> 8000
A17: Người 2 | B17: Nhóm 23 | C17: 13 | D17: ='Trân'!C70 -> 8000
A18: Người 2 | B18: Nhóm 26 | C18: 16 | D18: ='Trân'!C88 -> 8000
A19: Người 2 | B19: Nhóm 31 | C19: 24 | D19: ='Trân'!C114 -> 8000
A20: Người 2 | B20: Nhóm 34 | C20: 37 | D20: ='Trân'!C153 -> 8000
A21: Người 2 | B21: Nhóm 39 | C21: 152 | D21: ='Trân'!C307 -> 8000
A22: Người 3 | B22: Nhóm 3 | C22: 9 | D22: ='Nguyên'!C11 -> 8000
A23: Người 3 | B23: Nhóm 6 | C23: 9 | D23: ='Nguyên'!C22 -> 8000
A24: Người 3 | B24: Nhóm 11 | C24: 9 | D24: ='Nguyên'!C33 -> 8000
A25: Người 3 | B25: Nhóm 14 | C25: 9 | D25: ='Nguyên'!C44 -> 8000
A26: Người 3 | B26: Nhóm 19 | C26: 9 | D26: ='Nguyên'!C55 -> 8000
A27: Người 3 | B27: Nhóm 22 | C27: 11 | D27: ='Nguyên'!C68 -> 8000
A28: Người 3 | B28: Nhóm 27 | C28: 16 | D28: ='Nguyên'!C86 -> 8000
A29: Người 3 | B29: Nhóm 30 | C29: 22 | D29: ='Nguyên'!C110 -> 8000
A30: Người 3 | B30: Nhóm 35 | C30: 44 | D30: ='Nguyên'!C156 -> 8000
A31: Người 3 | B31: Nhóm 38 | C31: 94 | D31: ='Nguyên'!C252 -> 8000
A32: Người 4 | B32: Nhóm 4 | C32: 9 | D32: ='Hiếu'!C11 -> 8000
A33: Người 4 | B33: Nhóm 5 | C33: 9 | D33: ='Hiếu'!C22 -> 8000
A34: Người 4 | B34: Nhóm 12 | C34: 9 | D34: ='Hiếu'!C33 -> 8000
A35: Người 4 | B35: Nhóm 13 | C35: 9 | D35: ='Hiếu'!C44 -> 8000
A36: Người 4 | B36: Nhóm 20 | C36: 9 | D36: ='Hiếu'!C55 -> 8000
A37: Người 4 | B37: Nhóm 21 | C37: 11 | D37: ='Hiếu'!C68 -> 8000
A38: Người 4 | B38: Nhóm 28 | C38: 18 | D38: ='Hiếu'!C88 -> 8000
A39: Người 4 | B39: Nhóm 29 | C39: 19 | D39: ='Hiếu'!C109 -> 8000
A40: Người 4 | B40: Nhóm 36 | C40: 53 | D40: ='Hiếu'!C164 -> 8000
A41: Người 4 | B41: Nhóm 37 | C41: 67 | D41: ='Hiếu'!C233 -> 8000
A42: Tổng | C42: =SUM(C2:C41) -> 1603 | D42: =SUM(D2:D41) -> 319764
A44: Mỗi địa điểm tính tối đa 1035 reviews; mỗi nhóm = 1 acc (~8.000). 40 nhóm chia 4 người, mỗi người 10 nhóm (xếp xen kẽ để khối lượng đều nhau).
